Workbook

Sheet Lisez-moi
A1: Comparatif des fonctionnalités CMS
A2: Analyse réalisée le 25 octobre 2026 à partir de la documentation officielle de chaque CMS. Base de travail pour concevoir un CMS Laravel / Filament.
A4: Onglets
A5: Synthèse | B5: Couverture par CMS et par catégorie (formules calculées depuis la Matrice)
A6: Priorisation | B6: Grille enrichie (grille + ajouts hors grille) classée MVP / V1 / V2, avec différenciants et briques Laravel/Filament
A7: Matrice | B7: 211 fonctionnalités × CMS, statut coloré. Filtrable.
A8: Détails | B8: Une ligne par fonctionnalité et par CMS : statut, explication, source
A9: Hors grille | B9: Fonctionnalités relevées en dehors de la grille — pistes d'ajout
A10: Inspirations | B10: Points forts, idées à reprendre et limites de chaque CMS
A12: Légende des statuts
A13: Natif | B13: Inclus dans le cœur, sans extension
A14: Officiel | B14: Extension, add-on ou édition de l'éditeur du CMS (« Payant : » dans le détail si payant)
A15: Tiers | B15: Uniquement via une extension tierce
A16: Partiel | B16: Existe mais limité (voir le détail)
A17: Absent | B17: N'existe pas, même via extension connue
A18: ? | B18: Non confirmé après recherche
A19: Info | B19: Réponse factuelle (licence, moteur, popularité…), voir Détails
A21: CMS analysés
A22: CMS | B22: Version analysée | C22: Licence | D22: Stack
A23: WordPress | B23: 7.1.3 (6 octobre 2026) | C23: GPLv2 ou ultérieure | D23: PHP 7.4+ (8.3+ recommandé) / pas de framework (API maison), React pour l'éditeur / MySQL ou MariaDB
A24: Drupal | B24: Drupal core 11.4.11 (octobre 2026) ; Drupal CMS 2.2.7 (23 octobre 2026) ; Canvas 1.12 | C24: GPL-2.0-or-later | D24: PHP 8.3+ / Symfony 7 + Twig / MySQL-MariaDB, PostgreSQL, SQLite
A25: Craft CMS | B25: 5.11.5.1 (8 octobre 2026) | C25: Craft License (propriétaire, source disponible) ; édition Solo gratuite, Team/Pro payantes | D25: PHP 8.2+ / Yii 2 / Twig / MySQL, MariaDB ou PostgreSQL ; panneau en JS/Vue
A26: Kirby | B26: 5.6.1 (6 octobre 2026) ; 6.0.0-beta.1 en test | C26: Propriétaire (code source public), licence payante par site : Basic 99 €, Enterprise 349 € | D26: PHP 8.2-8.5 / framework maison (Panel Vue 2→3) / flat-file (fichiers texte), Db MySQL/SQLite optionnelle
A27: Statamic | B27: 6.38.0 (23 octobre 2026) | C27: Core gratuit (licence propriétaire Statamic LLC, code source ouvert) ; Pro commercial 349 $/site | D27: PHP 8.3+ / Laravel 12-13 / flat-file (YAML/Markdown, Stache) ou base SQL via Eloquent Driver ; CP Vue 3 + Inertia + Tailwind 4
A28: October CMS | B28: 4.4.11 (12 octobre 2026) | C28: Propriétaire (EULA Responsiv Pty Ltd), code source public ; licence gratuite la 1re année puis 39 $/site/an pour les mises à jour | D28: PHP 8.2+ / Laravel 12 / Twig 3 / MySQL, MariaDB, PostgreSQL, SQLite ; backend Vue 3
A29: Grav | B29: 2.2.13 (23 octobre 2026) | C29: MIT | D29: PHP 8.3+ / composants Symfony 7, Twig 3 / flat-file (Markdown + YAML), sans base de données ; Admin2 en SvelteKit
A30: Payload | B30: 3.92.0 (22 octobre 2026) | C30: MIT (cœur et plugins @payloadcms/*) ; fonctions Enterprise commerciales | D30: TypeScript / Node.js, Next.js (React) / MongoDB, PostgreSQL, SQLite, Cloudflare D1
A31: TallCMS | B31: 4.9.1 (21 septembre 2026) | C31: MIT (Core) ; Pro, Multisite et Billing sous licence commerciale | D31: PHP 8.2+ / Laravel 12-13, Filament 5, Livewire 4, Tailwind v4 + daisyUI / MySQL, MariaDB, SQLite
A32: Lara Zeus Sky | B32: 5.0.1 (29 avril 2026) | C32: MIT | D32: PHP 8.2+ / Laravel + Filament 5 (TALL : Livewire, Alpine, Tailwind) / base relationnelle via Eloquent
A34: Note : les statuts reflètent la documentation consultée à la date d'analyse. Les projets jeunes (TallCMS, Sky) comportent davantage de « ? ». Vérifier les points décisifs avant de s'en servir.

Sheet Synthèse
A1: Synthèse de couverture
A2: Toutes les valeurs sont calculées depuis l'onglet Matrice.
A4: CMS | B4: Natif | C4: Officiel | D4: Tiers | E4: Partiel | F4: Absent | G4: ? | H4: Info | I4: Total | J4: % disponible (natif+officiel) | K4: % avec extension (natif+off.+tiers)
A5: WordPress | B5: =COUNTIF(Matrice!$D$2:$D$212,"Natif") -> 81 | C5: =COUNTIF(Matrice!$D$2:$D$212,"Officiel") -> 49 | D5: =COUNTIF(Matrice!$D$2:$D$212,"Tiers") -> 30 | E5: =COUNTIF(Matrice!$D$2:$D$212,"Partiel") -> 39 | F5: =COUNTIF(Matrice!$D$2:$D$212,"Absent") -> 2 | G5: =COUNTIF(Matrice!$D$2:$D$212,"?") -> 0 | H5: =COUNTIF(Matrice!$D$2:$D$212,"Info") -> 10 | I5: =SUM(B5:H5) -> 211 | J5: =IFERROR((B5+C5)/(I5-H5),0) -> 0.64676617 | K5: =IFERROR((B5+C5+D5)/(I5-H5),0) -> 0.7960199
A6: Drupal | B6: =COUNTIF(Matrice!$E$2:$E$212,"Natif") -> 87 | C6: =COUNTIF(Matrice!$E$2:$E$212,"Officiel") -> 11 | D6: =COUNTIF(Matrice!$E$2:$E$212,"Tiers") -> 67 | E6: =COUNTIF(Matrice!$E$2:$E$212,"Partiel") -> 34 | F6: =COUNTIF(Matrice!$E$2:$E$212,"Absent") -> 2 | G6: =COUNTIF(Matrice!$E$2:$E$212,"?") -> 0 | H6: =COUNTIF(Matrice!$E$2:$E$212,"Info") -> 10 | I6: =SUM(B6:H6) -> 211 | J6: =IFERROR((B6+C6)/(I6-H6),0) -> 0.48756219 | K6: =IFERROR((B6+C6+D6)/(I6-H6),0) -> 0.82089552
A7: Craft CMS | B7: =COUNTIF(Matrice!$F$2:$F$212,"Natif") -> 95 | C7: =COUNTIF(Matrice!$F$2:$F$212,"Officiel") -> 26 | D7: =COUNTIF(Matrice!$F$2:$F$212,"Tiers") -> 34 | E7: =COUNTIF(Matrice!$F$2:$F$212,"Partiel") -> 28 | F7: =COUNTIF(Matrice!$F$2:$F$212,"Absent") -> 18 | G7: =COUNTIF(Matrice!$F$2:$F$212,"?") -> 0 | H7: =COUNTIF(Matrice!$F$2:$F$212,"Info") -> 10 | I7: =SUM(B7:H7) -> 211 | J7: =IFERROR((B7+C7)/(I7-H7),0) -> 0.60199005 | K7: =IFERROR((B7+C7+D7)/(I7-H7),0) -> 0.77114428
A8: Kirby | B8: =COUNTIF(Matrice!$G$2:$G$212,"Natif") -> 74 | C8: =COUNTIF(Matrice!$G$2:$G$212,"Officiel") -> 6 | D8: =COUNTIF(Matrice!$G$2:$G$212,"Tiers") -> 52 | E8: =COUNTIF(Matrice!$G$2:$G$212,"Partiel") -> 47 | F8: =COUNTIF(Matrice!$G$2:$G$212,"Absent") -> 22 | G8: =COUNTIF(Matrice!$G$2:$G$212,"?") -> 0 | H8: =COUNTIF(Matrice!$G$2:$G$212,"Info") -> 10 | I8: =SUM(B8:H8) -> 211 | J8: =IFERROR((B8+C8)/(I8-H8),0) -> 0.39800995 | K8: =IFERROR((B8+C8+D8)/(I8-H8),0) -> 0.65671642
A9: Statamic | B9: =COUNTIF(Matrice!$H$2:$H$212,"Natif") -> 100 | C9: =COUNTIF(Matrice!$H$2:$H$212,"Officiel") -> 40 | D9: =COUNTIF(Matrice!$H$2:$H$212,"Tiers") -> 19 | E9: =COUNTIF(Matrice!$H$2:$H$212,"Partiel") -> 19 | F9: =COUNTIF(Matrice!$H$2:$H$212,"Absent") -> 21 | G9: =COUNTIF(Matrice!$H$2:$H$212,"?") -> 2 | H9: =COUNTIF(Matrice!$H$2:$H$212,"Info") -> 10 | I9: =SUM(B9:H9) -> 211 | J9: =IFERROR((B9+C9)/(I9-H9),0) -> 0.69651741 | K9: =IFERROR((B9+C9+D9)/(I9-H9),0) -> 0.79104478
A10: October CMS | B10: =COUNTIF(Matrice!$I$2:$I$212,"Natif") -> 98 | C10: =COUNTIF(Matrice!$I$2:$I$212,"Officiel") -> 11 | D10: =COUNTIF(Matrice!$I$2:$I$212,"Tiers") -> 15 | E10: =COUNTIF(Matrice!$I$2:$I$212,"Partiel") -> 51 | F10: =COUNTIF(Matrice!$I$2:$I$212,"Absent") -> 23 | G10: =COUNTIF(Matrice!$I$2:$I$212,"?") -> 3 | H10: =COUNTIF(Matrice!$I$2:$I$212,"Info") -> 10 | I10: =SUM(B10:H10) -> 211 | J10: =IFERROR((B10+C10)/(I10-H10),0) -> 0.54228856 | K10: =IFERROR((B10+C10+D10)/(I10-H10),0) -> 0.61691542
A11: Grav | B11: =COUNTIF(Matrice!$J$2:$J$212,"Natif") -> 68 | C11: =COUNTIF(Matrice!$J$2:$J$212,"Officiel") -> 61 | D11: =COUNTIF(Matrice!$J$2:$J$212,"Tiers") -> 5 | E11: =COUNTIF(Matrice!$J$2:$J$212,"Partiel") -> 38 | F11: =COUNTIF(Matrice!$J$2:$J$212,"Absent") -> 24 | G11: =COUNTIF(Matrice!$J$2:$J$212,"?") -> 5 | H11: =COUNTIF(Matrice!$J$2:$J$212,"Info") -> 10 | I11: =SUM(B11:H11) -> 211 | J11: =IFERROR((B11+C11)/(I11-H11),0) -> 0.64179104 | K11: =IFERROR((B11+C11+D11)/(I11-H11),0) -> 0.66666667
A12: Payload | B12: =COUNTIF(Matrice!$K$2:$K$212,"Natif") -> 88 | C12: =COUNTIF(Matrice!$K$2:$K$212,"Officiel") -> 29 | D12: =COUNTIF(Matrice!$K$2:$K$212,"Tiers") -> 2 | E12: =COUNTIF(Matrice!$K$2:$K$212,"Partiel") -> 45 | F12: =COUNTIF(Matrice!$K$2:$K$212,"Absent") -> 37 | G12: =COUNTIF(Matrice!$K$2:$K$212,"?") -> 0 | H12: =COUNTIF(Matrice!$K$2:$K$212,"Info") -> 10 | I12: =SUM(B12:H12) -> 211 | J12: =IFERROR((B12+C12)/(I12-H12),0) -> 0.58208955 | K12: =IFERROR((B12+C12+D12)/(I12-H12),0) -> 0.5920398
A13: TallCMS | B13: =COUNTIF(Matrice!$L$2:$L$212,"Natif") -> 86 | C13: =COUNTIF(Matrice!$L$2:$L$212,"Officiel") -> 9 | D13: =COUNTIF(Matrice!$L$2:$L$212,"Tiers") -> 4 | E13: =COUNTIF(Matrice!$L$2:$L$212,"Partiel") -> 52 | F13: =COUNTIF(Matrice!$L$2:$L$212,"Absent") -> 47 | G13: =COUNTIF(Matrice!$L$2:$L$212,"?") -> 3 | H13: =COUNTIF(Matrice!$L$2:$L$212,"Info") -> 10 | I13: =SUM(B13:H13) -> 211 | J13: =IFERROR((B13+C13)/(I13-H13),0) -> 0.47263682 | K13: =IFERROR((B13+C13+D13)/(I13-H13),0) -> 0.49253731
A14: Lara Zeus Sky | B14: =COUNTIF(Matrice!$M$2:$M$212,"Natif") -> 52 | C14: =COUNTIF(Matrice!$M$2:$M$212,"Officiel") -> 8 | D14: =COUNTIF(Matrice!$M$2:$M$212,"Tiers") -> 6 | E14: =COUNTIF(Matrice!$M$2:$M$212,"Partiel") -> 45 | F14: =COUNTIF(Matrice!$M$2:$M$212,"Absent") -> 86 | G14: =COUNTIF(Matrice!$M$2:$M$212,"?") -> 4 | H14: =COUNTIF(Matrice!$M$2:$M$212,"Info") -> 10 | I14: =SUM(B14:H14) -> 211 | J14: =IFERROR((B14+C14)/(I14-H14),0) -> 0.29850746 | K14: =IFERROR((B14+C14+D14)/(I14-H14),0) -> 0.32835821
A15: « % disponible » exclut les lignes Info du dénominateur.
A17: Disponibilité (natif + officiel) par catégorie
A18: Bloc | B18: Catégorie | C18: Nb fonct. | D18: WordPress | E18: Drupal | F18: Craft CMS | G18: Kirby | H18: Statamic | I18: October CMS | J18: Grav | K18: Payload | L18: TallCMS | M18: Lara Zeus Sky
A19: Contenu | B19: Modélisation de contenu | C19: 13 | D19: =IFERROR((COUNTIF(Matrice!$D$2:$D$14,"Natif")+COUNTIF(Matrice!$D$2:$D$14,"Officiel"))/(C19-COUNTIF(Matrice!$D$2:$D$14,"Info")),0) -> 0.92307692 | E19: =IFERROR((COUNTIF(Matrice!$E$2:$E$14,"Natif")+COUNTIF(Matrice!$E$2:$E$14,"Officiel"))/(C19-COUNTIF(Matrice!$E$2:$E$14,"Info")),0) -> 0.46153846 | F19: =IFERROR((COUNTIF(Matrice!$F$2:$F$14,"Natif")+COUNTIF(Matrice!$F$2:$F$14,"Officiel"))/(C19-COUNTIF(Matrice!$F$2:$F$14,"Info")),0) -> 0.92307692 | G19: =IFERROR((COUNTIF(Matrice!$G$2:$G$14,"Natif")+COUNTIF(Matrice!$G$2:$G$14,"Officiel"))/(C19-COUNTIF(Matrice!$G$2:$G$14,"Info")),0) -> 0.61538462 | H19: =IFERROR((COUNTIF(Matrice!$H$2:$H$14,"Natif")+COUNTIF(Matrice!$H$2:$H$14,"Officiel"))/(C19-COUNTIF(Matrice!$H$2:$H$14,"Info")),0) -> 0.92307692 | I19: =IFERROR((COUNTIF(Matrice!$I$2:$I$14,"Natif")+COUNTIF(Matrice!$I$2:$I$14,"Officiel"))/(C19-COUNTIF(Matrice!$I$2:$I$14,"Info")),0) -> 0.76923077 | J19: =IFERROR((COUNTIF(Matrice!$J$2:$J$14,"Natif")+COUNTIF(Matrice!$J$2:$J$14,"Officiel"))/(C19-COUNTIF(Matrice!$J$2:$J$14,"Info")),0) -> 0.61538462 | K19: =IFERROR((COUNTIF(Matrice!$K$2:$K$14,"Natif")+COUNTIF(Matrice!$K$2:$K$14,"Officiel"))/(C19-COUNTIF(Matrice!$K$2:$K$14,"Info")),0) -> 0.84615385 | L19: =IFERROR((COUNTIF(Matrice!$L$2:$L$14,"Natif")+COUNTIF(Matrice!$L$2:$L$14,"Officiel"))/(C19-COUNTIF(Matrice!$L$2:$L$14,"Info")),0) -> 0.30769231 | M19: =IFERROR((COUNTIF(Matrice!$M$2:$M$14,"Natif")+COUNTIF(Matrice!$M$2:$M$14,"Officiel"))/(C19-COUNTIF(Matrice!$M$2:$M$14,"Info")),0) -> 0.23076923
A20: Contenu | B20: Édition et blocs | C20: 11 | D20: =IFERROR((COUNTIF(Matrice!$D$15:$D$25,"Natif")+COUNTIF(Matrice!$D$15:$D$25,"Officiel"))/(C20-COUNTIF(Matrice!$D$15:$D$25,"Info")),0) -> 0.81818182 | E20: =IFERROR((COUNTIF(Matrice!$E$15:$E$25,"Natif")+COUNTIF(Matrice!$E$15:$E$25,"Officiel"))/(C20-COUNTIF(Matrice!$E$15:$E$25,"Info")),0) -> 0.81818182 | F20: =IFERROR((COUNTIF(Matrice!$F$15:$F$25,"Natif")+COUNTIF(Matrice!$F$15:$F$25,"Officiel"))/(C20-COUNTIF(Matrice!$F$15:$F$25,"Info")),0) -> 0.63636364 | G20: =IFERROR((COUNTIF(Matrice!$G$15:$G$25,"Natif")+COUNTIF(Matrice!$G$15:$G$25,"Officiel"))/(C20-COUNTIF(Matrice!$G$15:$G$25,"Info")),0) -> 0.63636364 | H20: =IFERROR((COUNTIF(Matrice!$H$15:$H$25,"Natif")+COUNTIF(Matrice!$H$15:$H$25,"Officiel"))/(C20-COUNTIF(Matrice!$H$15:$H$25,"Info")),0) -> 0.63636364 | I20: =IFERROR((COUNTIF(Matrice!$I$15:$I$25,"Natif")+COUNTIF(Matrice!$I$15:$I$25,"Officiel"))/(C20-COUNTIF(Matrice!$I$15:$I$25,"Info")),0) -> 0.54545455 | J20: =IFERROR((COUNTIF(Matrice!$J$15:$J$25,"Natif")+COUNTIF(Matrice!$J$15:$J$25,"Officiel"))/(C20-COUNTIF(Matrice!$J$15:$J$25,"Info")),0) -> 0.63636364 | K20: =IFERROR((COUNTIF(Matrice!$K$15:$K$25,"Natif")+COUNTIF(Matrice!$K$15:$K$25,"Officiel"))/(C20-COUNTIF(Matrice!$K$15:$K$25,"Info")),0) -> 0.90909091 | L20: =IFERROR((COUNTIF(Matrice!$L$15:$L$25,"Natif")+COUNTIF(Matrice!$L$15:$L$25,"Officiel"))/(C20-COUNTIF(Matrice!$L$15:$L$25,"Info")),0) -> 0.45454545 | M20: =IFERROR((COUNTIF(Matrice!$M$15:$M$25,"Natif")+COUNTIF(Matrice!$M$15:$M$25,"Officiel"))/(C20-COUNTIF(Matrice!$M$15:$M$25,"Info")),0) -> 0.27272727
A21: Contenu | B21: Médias | C21: 10 | D21: =IFERROR((COUNTIF(Matrice!$D$26:$D$35,"Natif")+COUNTIF(Matrice!$D$26:$D$35,"Officiel"))/(C21-COUNTIF(Matrice!$D$26:$D$35,"Info")),0) -> 0.5 | E21: =IFERROR((COUNTIF(Matrice!$E$26:$E$35,"Natif")+COUNTIF(Matrice!$E$26:$E$35,"Officiel"))/(C21-COUNTIF(Matrice!$E$26:$E$35,"Info")),0) -> 0.5 | F21: =IFERROR((COUNTIF(Matrice!$F$26:$F$35,"Natif")+COUNTIF(Matrice!$F$26:$F$35,"Officiel"))/(C21-COUNTIF(Matrice!$F$26:$F$35,"Info")),0) -> 0.9 | G21: =IFERROR((COUNTIF(Matrice!$G$26:$G$35,"Natif")+COUNTIF(Matrice!$G$26:$G$35,"Officiel"))/(C21-COUNTIF(Matrice!$G$26:$G$35,"Info")),0) -> 0.6 | H21: =IFERROR((COUNTIF(Matrice!$H$26:$H$35,"Natif")+COUNTIF(Matrice!$H$26:$H$35,"Officiel"))/(C21-COUNTIF(Matrice!$H$26:$H$35,"Info")),0) -> 0.9 | I21: =IFERROR((COUNTIF(Matrice!$I$26:$I$35,"Natif")+COUNTIF(Matrice!$I$26:$I$35,"Officiel"))/(C21-COUNTIF(Matrice!$I$26:$I$35,"Info")),0) -> 0.6 | J21: =IFERROR((COUNTIF(Matrice!$J$26:$J$35,"Natif")+COUNTIF(Matrice!$J$26:$J$35,"Officiel"))/(C21-COUNTIF(Matrice!$J$26:$J$35,"Info")),0) -> 0.7 | K21: =IFERROR((COUNTIF(Matrice!$K$26:$K$35,"Natif")+COUNTIF(Matrice!$K$26:$K$35,"Officiel"))/(C21-COUNTIF(Matrice!$K$26:$K$35,"Info")),0) -> 0.8 | L21: =IFERROR((COUNTIF(Matrice!$L$26:$L$35,"Natif")+COUNTIF(Matrice!$L$26:$L$35,"Officiel"))/(C21-COUNTIF(Matrice!$L$26:$L$35,"Info")),0) -> 0.4 | M21: =IFERROR((COUNTIF(Matrice!$M$26:$M$35,"Natif")+COUNTIF(Matrice!$M$26:$M$35,"Officiel"))/(C21-COUNTIF(Matrice!$M$26:$M$35,"Info")),0) -> 0.3
A22: Contenu | B22: Versioning et planification | C22: 8 | D22: =IFERROR((COUNTIF(Matrice!$D$36:$D$43,"Natif")+COUNTIF(Matrice!$D$36:$D$43,"Officiel"))/(C22-COUNTIF(Matrice!$D$36:$D$43,"Info")),0) -> 0.75 | E22: =IFERROR((COUNTIF(Matrice!$E$36:$E$43,"Natif")+COUNTIF(Matrice!$E$36:$E$43,"Officiel"))/(C22-COUNTIF(Matrice!$E$36:$E$43,"Info")),0) -> 0.375 | F22: =IFERROR((COUNTIF(Matrice!$F$36:$F$43,"Natif")+COUNTIF(Matrice!$F$36:$F$43,"Officiel"))/(C22-COUNTIF(Matrice!$F$36:$F$43,"Info")),0) -> 0.875 | G22: =IFERROR((COUNTIF(Matrice!$G$36:$G$43,"Natif")+COUNTIF(Matrice!$G$36:$G$43,"Officiel"))/(C22-COUNTIF(Matrice!$G$36:$G$43,"Info")),0) -> 0.25 | H22: =IFERROR((COUNTIF(Matrice!$H$36:$H$43,"Natif")+COUNTIF(Matrice!$H$36:$H$43,"Officiel"))/(C22-COUNTIF(Matrice!$H$36:$H$43,"Info")),0) -> 0.625 | I22: =IFERROR((COUNTIF(Matrice!$I$36:$I$43,"Natif")+COUNTIF(Matrice!$I$36:$I$43,"Officiel"))/(C22-COUNTIF(Matrice!$I$36:$I$43,"Info")),0) -> 0.625 | J22: =IFERROR((COUNTIF(Matrice!$J$36:$J$43,"Natif")+COUNTIF(Matrice!$J$36:$J$43,"Officiel"))/(C22-COUNTIF(Matrice!$J$36:$J$43,"Info")),0) -> 0.875 | K22: =IFERROR((COUNTIF(Matrice!$K$36:$K$43,"Natif")+COUNTIF(Matrice!$K$36:$K$43,"Officiel"))/(C22-COUNTIF(Matrice!$K$36:$K$43,"Info")),0) -> 1 | L22: =IFERROR((COUNTIF(Matrice!$L$36:$L$43,"Natif")+COUNTIF(Matrice!$L$36:$L$43,"Officiel"))/(C22-COUNTIF(Matrice!$L$36:$L$43,"Info")),0) -> 0.75 | M22: =IFERROR((COUNTIF(Matrice!$M$36:$M$43,"Natif")+COUNTIF(Matrice!$M$36:$M$43,"Officiel"))/(C22-COUNTIF(Matrice!$M$36:$M$43,"Info")),0) -> 0.375
A23: Contenu | B23: Recherche | C23: 6 | D23: =IFERROR((COUNTIF(Matrice!$D$44:$D$49,"Natif")+COUNTIF(Matrice!$D$44:$D$49,"Officiel"))/(C23-COUNTIF(Matrice!$D$44:$D$49,"Info")),0) -> 0.66666667 | E23: =IFERROR((COUNTIF(Matrice!$E$44:$E$49,"Natif")+COUNTIF(Matrice!$E$44:$E$49,"Officiel"))/(C23-COUNTIF(Matrice!$E$44:$E$49,"Info")),0) -> 0.16666667 | F23: =IFERROR((COUNTIF(Matrice!$F$44:$F$49,"Natif")+COUNTIF(Matrice!$F$44:$F$49,"Officiel"))/(C23-COUNTIF(Matrice!$F$44:$F$49,"Info")),0) -> 0.66666667 | G23: =IFERROR((COUNTIF(Matrice!$G$44:$G$49,"Natif")+COUNTIF(Matrice!$G$44:$G$49,"Officiel"))/(C23-COUNTIF(Matrice!$G$44:$G$49,"Info")),0) -> 0.33333333 | H23: =IFERROR((COUNTIF(Matrice!$H$44:$H$49,"Natif")+COUNTIF(Matrice!$H$44:$H$49,"Officiel"))/(C23-COUNTIF(Matrice!$H$44:$H$49,"Info")),0) -> 0.83333333 | I23: =IFERROR((COUNTIF(Matrice!$I$44:$I$49,"Natif")+COUNTIF(Matrice!$I$44:$I$49,"Officiel"))/(C23-COUNTIF(Matrice!$I$44:$I$49,"Info")),0) -> 0.16666667 | J23: =IFERROR((COUNTIF(Matrice!$J$44:$J$49,"Natif")+COUNTIF(Matrice!$J$44:$J$49,"Officiel"))/(C23-COUNTIF(Matrice!$J$44:$J$49,"Info")),0) -> 0.83333333 | K23: =IFERROR((COUNTIF(Matrice!$K$44:$K$49,"Natif")+COUNTIF(Matrice!$K$44:$K$49,"Officiel"))/(C23-COUNTIF(Matrice!$K$44:$K$49,"Info")),0) -> 0.66666667 | L23: =IFERROR((COUNTIF(Matrice!$L$44:$L$49,"Natif")+COUNTIF(Matrice!$L$44:$L$49,"Officiel"))/(C23-COUNTIF(Matrice!$L$44:$L$49,"Info")),0) -> 0.33333333 | M23: =IFERROR((COUNTIF(Matrice!$M$44:$M$49,"Natif")+COUNTIF(Matrice!$M$44:$M$49,"Officiel"))/(C23-COUNTIF(Matrice!$M$44:$M$49,"Info")),0) -> 0.33333333
A24: Contenu | B24: Formulaires | C24: 7 | D24: =IFERROR((COUNTIF(Matrice!$D$50:$D$56,"Natif")+COUNTIF(Matrice!$D$50:$D$56,"Officiel"))/(C24-COUNTIF(Matrice!$D$50:$D$56,"Info")),0) -> 1 | E24: =IFERROR((COUNTIF(Matrice!$E$50:$E$56,"Natif")+COUNTIF(Matrice!$E$50:$E$56,"Officiel"))/(C24-COUNTIF(Matrice!$E$50:$E$56,"Info")),0) -> 0 | F24: =IFERROR((COUNTIF(Matrice!$F$50:$F$56,"Natif")+COUNTIF(Matrice!$F$50:$F$56,"Officiel"))/(C24-COUNTIF(Matrice!$F$50:$F$56,"Info")),0) -> 0.42857143 | G24: =IFERROR((COUNTIF(Matrice!$G$50:$G$56,"Natif")+COUNTIF(Matrice!$G$50:$G$56,"Officiel"))/(C24-COUNTIF(Matrice!$G$50:$G$56,"Info")),0) -> 0 | H24: =IFERROR((COUNTIF(Matrice!$H$50:$H$56,"Natif")+COUNTIF(Matrice!$H$50:$H$56,"Officiel"))/(C24-COUNTIF(Matrice!$H$50:$H$56,"Info")),0) -> 1 | I24: =IFERROR((COUNTIF(Matrice!$I$50:$I$56,"Natif")+COUNTIF(Matrice!$I$50:$I$56,"Officiel"))/(C24-COUNTIF(Matrice!$I$50:$I$56,"Info")),0) -> 0.71428571 | J24: =IFERROR((COUNTIF(Matrice!$J$50:$J$56,"Natif")+COUNTIF(Matrice!$J$50:$J$56,"Officiel"))/(C24-COUNTIF(Matrice!$J$50:$J$56,"Info")),0) -> 0.57142857 | K24: =IFERROR((COUNTIF(Matrice!$K$50:$K$56,"Natif")+COUNTIF(Matrice!$K$50:$K$56,"Officiel"))/(C24-COUNTIF(Matrice!$K$50:$K$56,"Info")),0) -> 0.71428571 | L24: =IFERROR((COUNTIF(Matrice!$L$50:$L$56,"Natif")+COUNTIF(Matrice!$L$50:$L$56,"Officiel"))/(C24-COUNTIF(Matrice!$L$50:$L$56,"Info")),0) -> 0.28571429 | M24: =IFERROR((COUNTIF(Matrice!$M$50:$M$56,"Natif")+COUNTIF(Matrice!$M$50:$M$56,"Officiel"))/(C24-COUNTIF(Matrice!$M$50:$M$56,"Info")),0) -> 0.85714286
A25: Utilisateurs | B25: Utilisateurs et rôles | C25: 9 | D25: =IFERROR((COUNTIF(Matrice!$D$57:$D$65,"Natif")+COUNTIF(Matrice!$D$57:$D$65,"Officiel"))/(C25-COUNTIF(Matrice!$D$57:$D$65,"Info")),0) -> 0.44444444 | E25: =IFERROR((COUNTIF(Matrice!$E$57:$E$65,"Natif")+COUNTIF(Matrice!$E$57:$E$65,"Officiel"))/(C25-COUNTIF(Matrice!$E$57:$E$65,"Info")),0) -> 0.44444444 | F25: =IFERROR((COUNTIF(Matrice!$F$57:$F$65,"Natif")+COUNTIF(Matrice!$F$57:$F$65,"Officiel"))/(C25-COUNTIF(Matrice!$F$57:$F$65,"Info")),0) -> 1 | G25: =IFERROR((COUNTIF(Matrice!$G$57:$G$65,"Natif")+COUNTIF(Matrice!$G$57:$G$65,"Officiel"))/(C25-COUNTIF(Matrice!$G$57:$G$65,"Info")),0) -> 0.33333333 | H25: =IFERROR((COUNTIF(Matrice!$H$57:$H$65,"Natif")+COUNTIF(Matrice!$H$57:$H$65,"Officiel"))/(C25-COUNTIF(Matrice!$H$57:$H$65,"Info")),0) -> 0.88888889 | I25: =IFERROR((COUNTIF(Matrice!$I$57:$I$65,"Natif")+COUNTIF(Matrice!$I$57:$I$65,"Officiel"))/(C25-COUNTIF(Matrice!$I$57:$I$65,"Info")),0) -> 0.66666667 | J25: =IFERROR((COUNTIF(Matrice!$J$57:$J$65,"Natif")+COUNTIF(Matrice!$J$57:$J$65,"Officiel"))/(C25-COUNTIF(Matrice!$J$57:$J$65,"Info")),0) -> 0.77777778 | K25: =IFERROR((COUNTIF(Matrice!$K$57:$K$65,"Natif")+COUNTIF(Matrice!$K$57:$K$65,"Officiel"))/(C25-COUNTIF(Matrice!$K$57:$K$65,"Info")),0) -> 0.55555556 | L25: =IFERROR((COUNTIF(Matrice!$L$57:$L$65,"Natif")+COUNTIF(Matrice!$L$57:$L$65,"Officiel"))/(C25-COUNTIF(Matrice!$L$57:$L$65,"Info")),0) -> 0.44444444 | M25: =IFERROR((COUNTIF(Matrice!$M$57:$M$65,"Natif")+COUNTIF(Matrice!$M$57:$M$65,"Officiel"))/(C25-COUNTIF(Matrice!$M$57:$M$65,"Info")),0) -> 0.11111111
A26: Utilisateurs | B26: Workflows éditoriaux | C26: 6 | D26: =IFERROR((COUNTIF(Matrice!$D$66:$D$71,"Natif")+COUNTIF(Matrice!$D$66:$D$71,"Officiel"))/(C26-COUNTIF(Matrice!$D$66:$D$71,"Info")),0) -> 0.5 | E26: =IFERROR((COUNTIF(Matrice!$E$66:$E$71,"Natif")+COUNTIF(Matrice!$E$66:$E$71,"Officiel"))/(C26-COUNTIF(Matrice!$E$66:$E$71,"Info")),0) -> 0.33333333 | F26: =IFERROR((COUNTIF(Matrice!$F$66:$F$71,"Natif")+COUNTIF(Matrice!$F$66:$F$71,"Officiel"))/(C26-COUNTIF(Matrice!$F$66:$F$71,"Info")),0) -> 0 | G26: =IFERROR((COUNTIF(Matrice!$G$66:$G$71,"Natif")+COUNTIF(Matrice!$G$66:$G$71,"Officiel"))/(C26-COUNTIF(Matrice!$G$66:$G$71,"Info")),0) -> 0.16666667 | H26: =IFERROR((COUNTIF(Matrice!$H$66:$H$71,"Natif")+COUNTIF(Matrice!$H$66:$H$71,"Officiel"))/(C26-COUNTIF(Matrice!$H$66:$H$71,"Info")),0) -> 0.33333333 | I26: =IFERROR((COUNTIF(Matrice!$I$66:$I$71,"Natif")+COUNTIF(Matrice!$I$66:$I$71,"Officiel"))/(C26-COUNTIF(Matrice!$I$66:$I$71,"Info")),0) -> 0 | J26: =IFERROR((COUNTIF(Matrice!$J$66:$J$71,"Natif")+COUNTIF(Matrice!$J$66:$J$71,"Officiel"))/(C26-COUNTIF(Matrice!$J$66:$J$71,"Info")),0) -> 0.16666667 | K26: =IFERROR((COUNTIF(Matrice!$K$66:$K$71,"Natif")+COUNTIF(Matrice!$K$66:$K$71,"Officiel"))/(C26-COUNTIF(Matrice!$K$66:$K$71,"Info")),0) -> 0.83333333 | L26: =IFERROR((COUNTIF(Matrice!$L$66:$L$71,"Natif")+COUNTIF(Matrice!$L$66:$L$71,"Officiel"))/(C26-COUNTIF(Matrice!$L$66:$L$71,"Info")),0) -> 0.16666667 | M26: =IFERROR((COUNTIF(Matrice!$M$66:$M$71,"Natif")+COUNTIF(Matrice!$M$66:$M$71,"Officiel"))/(C26-COUNTIF(Matrice!$M$66:$M$71,"Info")),0) -> 0.16666667
A27: Utilisateurs | B27: Notifications et e-mails | C27: 5 | D27: =IFERROR((COUNTIF(Matrice!$D$72:$D$76,"Natif")+COUNTIF(Matrice!$D$72:$D$76,"Officiel"))/(C27-COUNTIF(Matrice!$D$72:$D$76,"Info")),0) -> 0.2 | E27: =IFERROR((COUNTIF(Matrice!$E$72:$E$76,"Natif")+COUNTIF(Matrice!$E$72:$E$76,"Officiel"))/(C27-COUNTIF(Matrice!$E$72:$E$76,"Info")),0) -> 0.2 | F27: =IFERROR((COUNTIF(Matrice!$F$72:$F$76,"Natif")+COUNTIF(Matrice!$F$72:$F$76,"Officiel"))/(C27-COUNTIF(Matrice!$F$72:$F$76,"Info")),0) -> 0.6 | G27: =IFERROR((COUNTIF(Matrice!$G$72:$G$76,"Natif")+COUNTIF(Matrice!$G$72:$G$76,"Officiel"))/(C27-COUNTIF(Matrice!$G$72:$G$76,"Info")),0) -> 0.2 | H27: =IFERROR((COUNTIF(Matrice!$H$72:$H$76,"Natif")+COUNTIF(Matrice!$H$72:$H$76,"Officiel"))/(C27-COUNTIF(Matrice!$H$72:$H$76,"Info")),0) -> 0.2 | I27: =IFERROR((COUNTIF(Matrice!$I$72:$I$76,"Natif")+COUNTIF(Matrice!$I$72:$I$76,"Officiel"))/(C27-COUNTIF(Matrice!$I$72:$I$76,"Info")),0) -> 0.8 | J27: =IFERROR((COUNTIF(Matrice!$J$72:$J$76,"Natif")+COUNTIF(Matrice!$J$72:$J$76,"Officiel"))/(C27-COUNTIF(Matrice!$J$72:$J$76,"Info")),0) -> 0.6 | K27: =IFERROR((COUNTIF(Matrice!$K$72:$K$76,"Natif")+COUNTIF(Matrice!$K$72:$K$76,"Officiel"))/(C27-COUNTIF(Matrice!$K$72:$K$76,"Info")),0) -> 0.4 | L27: =IFERROR((COUNTIF(Matrice!$L$72:$L$76,"Natif")+COUNTIF(Matrice!$L$72:$L$76,"Officiel"))/(C27-COUNTIF(Matrice!$L$72:$L$76,"Info")),0) -> 0.8 | M27: =IFERROR((COUNTIF(Matrice!$M$72:$M$76,"Natif")+COUNTIF(Matrice!$M$72:$M$76,"Officiel"))/(C27-COUNTIF(Matrice!$M$72:$M$76,"Info")),0) -> 0.2
A28: Diffusion | B28: Multilingue et multi-site | C28: 7 | D28: =IFERROR((COUNTIF(Matrice!$D$77:$D$83,"Natif")+COUNTIF(Matrice!$D$77:$D$83,"Officiel"))/(C28-COUNTIF(Matrice!$D$77:$D$83,"Info")),0) -> 0.28571429 | E28: =IFERROR((COUNTIF(Matrice!$E$77:$E$83,"Natif")+COUNTIF(Matrice!$E$77:$E$83,"Officiel"))/(C28-COUNTIF(Matrice!$E$77:$E$83,"Info")),0) -> 0.71428571 | F28: =IFERROR((COUNTIF(Matrice!$F$77:$F$83,"Natif")+COUNTIF(Matrice!$F$77:$F$83,"Officiel"))/(C28-COUNTIF(Matrice!$F$77:$F$83,"Info")),0) -> 0.71428571 | G28: =IFERROR((COUNTIF(Matrice!$G$77:$G$83,"Natif")+COUNTIF(Matrice!$G$77:$G$83,"Officiel"))/(C28-COUNTIF(Matrice!$G$77:$G$83,"Info")),0) -> 0.57142857 | H28: =IFERROR((COUNTIF(Matrice!$H$77:$H$83,"Natif")+COUNTIF(Matrice!$H$77:$H$83,"Officiel"))/(C28-COUNTIF(Matrice!$H$77:$H$83,"Info")),0) -> 0.85714286 | I28: =IFERROR((COUNTIF(Matrice!$I$77:$I$83,"Natif")+COUNTIF(Matrice!$I$77:$I$83,"Officiel"))/(C28-COUNTIF(Matrice!$I$77:$I$83,"Info")),0) -> 0.71428571 | J28: =IFERROR((COUNTIF(Matrice!$J$77:$J$83,"Natif")+COUNTIF(Matrice!$J$77:$J$83,"Officiel"))/(C28-COUNTIF(Matrice!$J$77:$J$83,"Info")),0) -> 0.42857143 | K28: =IFERROR((COUNTIF(Matrice!$K$77:$K$83,"Natif")+COUNTIF(Matrice!$K$77:$K$83,"Officiel"))/(C28-COUNTIF(Matrice!$K$77:$K$83,"Info")),0) -> 0.71428571 | L28: =IFERROR((COUNTIF(Matrice!$L$77:$L$83,"Natif")+COUNTIF(Matrice!$L$77:$L$83,"Officiel"))/(C28-COUNTIF(Matrice!$L$77:$L$83,"Info")),0) -> 0.85714286 | M28: =IFERROR((COUNTIF(Matrice!$M$77:$M$83,"Natif")+COUNTIF(Matrice!$M$77:$M$83,"Officiel"))/(C28-COUNTIF(Matrice!$M$77:$M$83,"Info")),0) -> 0.42857143
A29: Diffusion | B29: Routing | C29: 9 | D29: =IFERROR((COUNTIF(Matrice!$D$84:$D$92,"Natif")+COUNTIF(Matrice!$D$84:$D$92,"Officiel"))/(C29-COUNTIF(Matrice!$D$84:$D$92,"Info")),0) -> 0.55555556 | E29: =IFERROR((COUNTIF(Matrice!$E$84:$E$92,"Natif")+COUNTIF(Matrice!$E$84:$E$92,"Officiel"))/(C29-COUNTIF(Matrice!$E$84:$E$92,"Info")),0) -> 0.44444444 | F29: =IFERROR((COUNTIF(Matrice!$F$84:$F$92,"Natif")+COUNTIF(Matrice!$F$84:$F$92,"Officiel"))/(C29-COUNTIF(Matrice!$F$84:$F$92,"Info")),0) -> 0.55555556 | G29: =IFERROR((COUNTIF(Matrice!$G$84:$G$92,"Natif")+COUNTIF(Matrice!$G$84:$G$92,"Officiel"))/(C29-COUNTIF(Matrice!$G$84:$G$92,"Info")),0) -> 0.44444444 | H29: =IFERROR((COUNTIF(Matrice!$H$84:$H$92,"Natif")+COUNTIF(Matrice!$H$84:$H$92,"Officiel"))/(C29-COUNTIF(Matrice!$H$84:$H$92,"Info")),0) -> 1 | I29: =IFERROR((COUNTIF(Matrice!$I$84:$I$92,"Natif")+COUNTIF(Matrice!$I$84:$I$92,"Officiel"))/(C29-COUNTIF(Matrice!$I$84:$I$92,"Info")),0) -> 0.66666667 | J29: =IFERROR((COUNTIF(Matrice!$J$84:$J$92,"Natif")+COUNTIF(Matrice!$J$84:$J$92,"Officiel"))/(C29-COUNTIF(Matrice!$J$84:$J$92,"Info")),0) -> 0.66666667 | K29: =IFERROR((COUNTIF(Matrice!$K$84:$K$92,"Natif")+COUNTIF(Matrice!$K$84:$K$92,"Officiel"))/(C29-COUNTIF(Matrice!$K$84:$K$92,"Info")),0) -> 0.33333333 | L29: =IFERROR((COUNTIF(Matrice!$L$84:$L$92,"Natif")+COUNTIF(Matrice!$L$84:$L$92,"Officiel"))/(C29-COUNTIF(Matrice!$L$84:$L$92,"Info")),0) -> 0.44444444 | M29: =IFERROR((COUNTIF(Matrice!$M$84:$M$92,"Natif")+COUNTIF(Matrice!$M$84:$M$92,"Officiel"))/(C29-COUNTIF(Matrice!$M$84:$M$92,"Info")),0) -> 0.22222222
A30: Diffusion | B30: Templating | C30: 7 | D30: =IFERROR((COUNTIF(Matrice!$D$93:$D$99,"Natif")+COUNTIF(Matrice!$D$93:$D$99,"Officiel"))/(C30-COUNTIF(Matrice!$D$93:$D$99,"Info")),0) -> 1 | E30: =IFERROR((COUNTIF(Matrice!$E$93:$E$99,"Natif")+COUNTIF(Matrice!$E$93:$E$99,"Officiel"))/(C30-COUNTIF(Matrice!$E$93:$E$99,"Info")),0) -> 0.83333333 | F30: =IFERROR((COUNTIF(Matrice!$F$93:$F$99,"Natif")+COUNTIF(Matrice!$F$93:$F$99,"Officiel"))/(C30-COUNTIF(Matrice!$F$93:$F$99,"Info")),0) -> 0.5 | G30: =IFERROR((COUNTIF(Matrice!$G$93:$G$99,"Natif")+COUNTIF(Matrice!$G$93:$G$99,"Officiel"))/(C30-COUNTIF(Matrice!$G$93:$G$99,"Info")),0) -> 0.83333333 | H30: =IFERROR((COUNTIF(Matrice!$H$93:$H$99,"Natif")+COUNTIF(Matrice!$H$93:$H$99,"Officiel"))/(C30-COUNTIF(Matrice!$H$93:$H$99,"Info")),0) -> 0.66666667 | I30: =IFERROR((COUNTIF(Matrice!$I$93:$I$99,"Natif")+COUNTIF(Matrice!$I$93:$I$99,"Officiel"))/(C30-COUNTIF(Matrice!$I$93:$I$99,"Info")),0) -> 0.66666667 | J30: =IFERROR((COUNTIF(Matrice!$J$93:$J$99,"Natif")+COUNTIF(Matrice!$J$93:$J$99,"Officiel"))/(C30-COUNTIF(Matrice!$J$93:$J$99,"Info")),0) -> 0.83333333 | K30: =IFERROR((COUNTIF(Matrice!$K$93:$K$99,"Natif")+COUNTIF(Matrice!$K$93:$K$99,"Officiel"))/(C30-COUNTIF(Matrice!$K$93:$K$99,"Info")),0) -> 0 | L30: =IFERROR((COUNTIF(Matrice!$L$93:$L$99,"Natif")+COUNTIF(Matrice!$L$93:$L$99,"Officiel"))/(C30-COUNTIF(Matrice!$L$93:$L$99,"Info")),0) -> 0.83333333 | M30: =IFERROR((COUNTIF(Matrice!$M$93:$M$99,"Natif")+COUNTIF(Matrice!$M$93:$M$99,"Officiel"))/(C30-COUNTIF(Matrice!$M$93:$M$99,"Info")),0) -> 0.5
A31: Diffusion | B31: Thèmes et front-end | C31: 7 | D31: =IFERROR((COUNTIF(Matrice!$D$100:$D$106,"Natif")+COUNTIF(Matrice!$D$100:$D$106,"Officiel"))/(C31-COUNTIF(Matrice!$D$100:$D$106,"Info")),0) -> 0.71428571 | E31: =IFERROR((COUNTIF(Matrice!$E$100:$E$106,"Natif")+COUNTIF(Matrice!$E$100:$E$106,"Officiel"))/(C31-COUNTIF(Matrice!$E$100:$E$106,"Info")),0) -> 0.71428571 | F31: =IFERROR((COUNTIF(Matrice!$F$100:$F$106,"Natif")+COUNTIF(Matrice!$F$100:$F$106,"Officiel"))/(C31-COUNTIF(Matrice!$F$100:$F$106,"Info")),0) -> 0.28571429 | G31: =IFERROR((COUNTIF(Matrice!$G$100:$G$106,"Natif")+COUNTIF(Matrice!$G$100:$G$106,"Officiel"))/(C31-COUNTIF(Matrice!$G$100:$G$106,"Info")),0) -> 0.28571429 | H31: =IFERROR((COUNTIF(Matrice!$H$100:$H$106,"Natif")+COUNTIF(Matrice!$H$100:$H$106,"Officiel"))/(C31-COUNTIF(Matrice!$H$100:$H$106,"Info")),0) -> 0.57142857 | I31: =IFERROR((COUNTIF(Matrice!$I$100:$I$106,"Natif")+COUNTIF(Matrice!$I$100:$I$106,"Officiel"))/(C31-COUNTIF(Matrice!$I$100:$I$106,"Info")),0) -> 0.57142857 | J31: =IFERROR((COUNTIF(Matrice!$J$100:$J$106,"Natif")+COUNTIF(Matrice!$J$100:$J$106,"Officiel"))/(C31-COUNTIF(Matrice!$J$100:$J$106,"Info")),0) -> 0.85714286 | K31: =IFERROR((COUNTIF(Matrice!$K$100:$K$106,"Natif")+COUNTIF(Matrice!$K$100:$K$106,"Officiel"))/(C31-COUNTIF(Matrice!$K$100:$K$106,"Info")),0) -> 0.28571429 | L31: =IFERROR((COUNTIF(Matrice!$L$100:$L$106,"Natif")+COUNTIF(Matrice!$L$100:$L$106,"Officiel"))/(C31-COUNTIF(Matrice!$L$100:$L$106,"Info")),0) -> 0.71428571 | M31: =IFERROR((COUNTIF(Matrice!$M$100:$M$106,"Natif")+COUNTIF(Matrice!$M$100:$M$106,"Officiel"))/(C31-COUNTIF(Matrice!$M$100:$M$106,"Info")),0) -> 0.42857143
A32: Diffusion | B32: SEO | C32: 7 | D32: =IFERROR((COUNTIF(Matrice!$D$107:$D$113,"Natif")+COUNTIF(Matrice!$D$107:$D$113,"Officiel"))/(C32-COUNTIF(Matrice!$D$107:$D$113,"Info")),0) -> 0.42857143 | E32: =IFERROR((COUNTIF(Matrice!$E$107:$E$113,"Natif")+COUNTIF(Matrice!$E$107:$E$113,"Officiel"))/(C32-COUNTIF(Matrice!$E$107:$E$113,"Info")),0) -> 0 | F32: =IFERROR((COUNTIF(Matrice!$F$107:$F$113,"Natif")+COUNTIF(Matrice!$F$107:$F$113,"Officiel"))/(C32-COUNTIF(Matrice!$F$107:$F$113,"Info")),0) -> 0 | G32: =IFERROR((COUNTIF(Matrice!$G$107:$G$113,"Natif")+COUNTIF(Matrice!$G$107:$G$113,"Officiel"))/(C32-COUNTIF(Matrice!$G$107:$G$113,"Info")),0) -> 0 | H32: =IFERROR((COUNTIF(Matrice!$H$107:$H$113,"Natif")+COUNTIF(Matrice!$H$107:$H$113,"Officiel"))/(C32-COUNTIF(Matrice!$H$107:$H$113,"Info")),0) -> 0.85714286 | I32: =IFERROR((COUNTIF(Matrice!$I$107:$I$113,"Natif")+COUNTIF(Matrice!$I$107:$I$113,"Officiel"))/(C32-COUNTIF(Matrice!$I$107:$I$113,"Info")),0) -> 0.14285714 | J32: =IFERROR((COUNTIF(Matrice!$J$107:$J$113,"Natif")+COUNTIF(Matrice!$J$107:$J$113,"Officiel"))/(C32-COUNTIF(Matrice!$J$107:$J$113,"Info")),0) -> 0.85714286 | K32: =IFERROR((COUNTIF(Matrice!$K$107:$K$113,"Natif")+COUNTIF(Matrice!$K$107:$K$113,"Officiel"))/(C32-COUNTIF(Matrice!$K$107:$K$113,"Info")),0) -> 0.28571429 | L32: =IFERROR((COUNTIF(Matrice!$L$107:$L$113,"Natif")+COUNTIF(Matrice!$L$107:$L$113,"Officiel"))/(C32-COUNTIF(Matrice!$L$107:$L$113,"Info")),0) -> 0.71428571 | M32: =IFERROR((COUNTIF(Matrice!$M$107:$M$113,"Natif")+COUNTIF(Matrice!$M$107:$M$113,"Officiel"))/(C32-COUNTIF(Matrice!$M$107:$M$113,"Info")),0) -> 0.14285714
A33: Diffusion | B33: API et headless | C33: 8 | D33: =IFERROR((COUNTIF(Matrice!$D$114:$D$121,"Natif")+COUNTIF(Matrice!$D$114:$D$121,"Officiel"))/(C33-COUNTIF(Matrice!$D$114:$D$121,"Info")),0) -> 0.625 | E33: =IFERROR((COUNTIF(Matrice!$E$114:$E$121,"Natif")+COUNTIF(Matrice!$E$114:$E$121,"Officiel"))/(C33-COUNTIF(Matrice!$E$114:$E$121,"Info")),0) -> 0.75 | F33: =IFERROR((COUNTIF(Matrice!$F$114:$F$121,"Natif")+COUNTIF(Matrice!$F$114:$F$121,"Officiel"))/(C33-COUNTIF(Matrice!$F$114:$F$121,"Info")),0) -> 0.875 | G33: =IFERROR((COUNTIF(Matrice!$G$114:$G$121,"Natif")+COUNTIF(Matrice!$G$114:$G$121,"Officiel"))/(C33-COUNTIF(Matrice!$G$114:$G$121,"Info")),0) -> 0.375 | H33: =IFERROR((COUNTIF(Matrice!$H$114:$H$121,"Natif")+COUNTIF(Matrice!$H$114:$H$121,"Officiel"))/(C33-COUNTIF(Matrice!$H$114:$H$121,"Info")),0) -> 0.625 | I33: =IFERROR((COUNTIF(Matrice!$I$114:$I$121,"Natif")+COUNTIF(Matrice!$I$114:$I$121,"Officiel"))/(C33-COUNTIF(Matrice!$I$114:$I$121,"Info")),0) -> 0 | J33: =IFERROR((COUNTIF(Matrice!$J$114:$J$121,"Natif")+COUNTIF(Matrice!$J$114:$J$121,"Officiel"))/(C33-COUNTIF(Matrice!$J$114:$J$121,"Info")),0) -> 0.625 | K33: =IFERROR((COUNTIF(Matrice!$K$114:$K$121,"Natif")+COUNTIF(Matrice!$K$114:$K$121,"Officiel"))/(C33-COUNTIF(Matrice!$K$114:$K$121,"Info")),0) -> 0.875 | L33: =IFERROR((COUNTIF(Matrice!$L$114:$L$121,"Natif")+COUNTIF(Matrice!$L$114:$L$121,"Officiel"))/(C33-COUNTIF(Matrice!$L$114:$L$121,"Info")),0) -> 0.625 | M33: =IFERROR((COUNTIF(Matrice!$M$114:$M$121,"Natif")+COUNTIF(Matrice!$M$114:$M$121,"Officiel"))/(C33-COUNTIF(Matrice!$M$114:$M$121,"Info")),0) -> 0
A34: Diffusion | B34: Commerce | C34: 5 | D34: =IFERROR((COUNTIF(Matrice!$D$122:$D$126,"Natif")+COUNTIF(Matrice!$D$122:$D$126,"Officiel"))/(C34-COUNTIF(Matrice!$D$122:$D$126,"Info")),0) -> 0.8 | E34: =IFERROR((COUNTIF(Matrice!$E$122:$E$126,"Natif")+COUNTIF(Matrice!$E$122:$E$126,"Officiel"))/(C34-COUNTIF(Matrice!$E$122:$E$126,"Info")),0) -> 0 | F34: =IFERROR((COUNTIF(Matrice!$F$122:$F$126,"Natif")+COUNTIF(Matrice!$F$122:$F$126,"Officiel"))/(C34-COUNTIF(Matrice!$F$122:$F$126,"Info")),0) -> 0.8 | G34: =IFERROR((COUNTIF(Matrice!$G$122:$G$126,"Natif")+COUNTIF(Matrice!$G$122:$G$126,"Officiel"))/(C34-COUNTIF(Matrice!$G$122:$G$126,"Info")),0) -> 0 | H34: =IFERROR((COUNTIF(Matrice!$H$122:$H$126,"Natif")+COUNTIF(Matrice!$H$122:$H$126,"Officiel"))/(C34-COUNTIF(Matrice!$H$122:$H$126,"Info")),0) -> 0 | I34: =IFERROR((COUNTIF(Matrice!$I$122:$I$126,"Natif")+COUNTIF(Matrice!$I$122:$I$126,"Officiel"))/(C34-COUNTIF(Matrice!$I$122:$I$126,"Info")),0) -> 0.6 | J34: =IFERROR((COUNTIF(Matrice!$J$122:$J$126,"Natif")+COUNTIF(Matrice!$J$122:$J$126,"Officiel"))/(C34-COUNTIF(Matrice!$J$122:$J$126,"Info")),0) -> 0.6 | K34: =IFERROR((COUNTIF(Matrice!$K$122:$K$126,"Natif")+COUNTIF(Matrice!$K$122:$K$126,"Officiel"))/(C34-COUNTIF(Matrice!$K$122:$K$126,"Info")),0) -> 0.4 | L34: =IFERROR((COUNTIF(Matrice!$L$122:$L$126,"Natif")+COUNTIF(Matrice!$L$122:$L$126,"Officiel"))/(C34-COUNTIF(Matrice!$L$122:$L$126,"Info")),0) -> 0.2 | M34: =IFERROR((COUNTIF(Matrice!$M$122:$M$126,"Natif")+COUNTIF(Matrice!$M$122:$M$126,"Officiel"))/(C34-COUNTIF(Matrice!$M$122:$M$126,"Info")),0) -> 0
A35: Diffusion | B35: Accessibilité | C35: 4 | D35: =IFERROR((COUNTIF(Matrice!$D$127:$D$130,"Natif")+COUNTIF(Matrice!$D$127:$D$130,"Officiel"))/(C35-COUNTIF(Matrice!$D$127:$D$130,"Info")),0) -> 0.5 | E35: =IFERROR((COUNTIF(Matrice!$E$127:$E$130,"Natif")+COUNTIF(Matrice!$E$127:$E$130,"Officiel"))/(C35-COUNTIF(Matrice!$E$127:$E$130,"Info")),0) -> 0.75 | F35: =IFERROR((COUNTIF(Matrice!$F$127:$F$130,"Natif")+COUNTIF(Matrice!$F$127:$F$130,"Officiel"))/(C35-COUNTIF(Matrice!$F$127:$F$130,"Info")),0) -> 0.5 | G35: =IFERROR((COUNTIF(Matrice!$G$127:$G$130,"Natif")+COUNTIF(Matrice!$G$127:$G$130,"Officiel"))/(C35-COUNTIF(Matrice!$G$127:$G$130,"Info")),0) -> 0 | H35: =IFERROR((COUNTIF(Matrice!$H$127:$H$130,"Natif")+COUNTIF(Matrice!$H$127:$H$130,"Officiel"))/(C35-COUNTIF(Matrice!$H$127:$H$130,"Info")),0) -> 0 | I35: =IFERROR((COUNTIF(Matrice!$I$127:$I$130,"Natif")+COUNTIF(Matrice!$I$127:$I$130,"Officiel"))/(C35-COUNTIF(Matrice!$I$127:$I$130,"Info")),0) -> 0 | J35: =IFERROR((COUNTIF(Matrice!$J$127:$J$130,"Natif")+COUNTIF(Matrice!$J$127:$J$130,"Officiel"))/(C35-COUNTIF(Matrice!$J$127:$J$130,"Info")),0) -> 0 | K35: =IFERROR((COUNTIF(Matrice!$K$127:$K$130,"Natif")+COUNTIF(Matrice!$K$127:$K$130,"Officiel"))/(C35-COUNTIF(Matrice!$K$127:$K$130,"Info")),0) -> 0 | L35: =IFERROR((COUNTIF(Matrice!$L$127:$L$130,"Natif")+COUNTIF(Matrice!$L$127:$L$130,"Officiel"))/(C35-COUNTIF(Matrice!$L$127:$L$130,"Info")),0) -> 0 | M35: =IFERROR((COUNTIF(Matrice!$M$127:$M$130,"Natif")+COUNTIF(Matrice!$M$127:$M$130,"Officiel"))/(C35-COUNTIF(Matrice!$M$127:$M$130,"Info")),0) -> 0
A36: Technique | B36: Stockage des données | C36: 5 | D36: =IFERROR((COUNTIF(Matrice!$D$131:$D$135,"Natif")+COUNTIF(Matrice!$D$131:$D$135,"Officiel"))/(C36-COUNTIF(Matrice!$D$131:$D$135,"Info")),0) -> 0.25 | E36: =IFERROR((COUNTIF(Matrice!$E$131:$E$135,"Natif")+COUNTIF(Matrice!$E$131:$E$135,"Officiel"))/(C36-COUNTIF(Matrice!$E$131:$E$135,"Info")),0) -> 0.25 | F36: =IFERROR((COUNTIF(Matrice!$F$131:$F$135,"Natif")+COUNTIF(Matrice!$F$131:$F$135,"Officiel"))/(C36-COUNTIF(Matrice!$F$131:$F$135,"Info")),0) -> 0.25 | G36: =IFERROR((COUNTIF(Matrice!$G$131:$G$135,"Natif")+COUNTIF(Matrice!$G$131:$G$135,"Officiel"))/(C36-COUNTIF(Matrice!$G$131:$G$135,"Info")),0) -> 0.75 | H36: =IFERROR((COUNTIF(Matrice!$H$131:$H$135,"Natif")+COUNTIF(Matrice!$H$131:$H$135,"Officiel"))/(C36-COUNTIF(Matrice!$H$131:$H$135,"Info")),0) -> 1 | I36: =IFERROR((COUNTIF(Matrice!$I$131:$I$135,"Natif")+COUNTIF(Matrice!$I$131:$I$135,"Officiel"))/(C36-COUNTIF(Matrice!$I$131:$I$135,"Info")),0) -> 0.5 | J36: =IFERROR((COUNTIF(Matrice!$J$131:$J$135,"Natif")+COUNTIF(Matrice!$J$131:$J$135,"Officiel"))/(C36-COUNTIF(Matrice!$J$131:$J$135,"Info")),0) -> 0.5 | K36: =IFERROR((COUNTIF(Matrice!$K$131:$K$135,"Natif")+COUNTIF(Matrice!$K$131:$K$135,"Officiel"))/(C36-COUNTIF(Matrice!$K$131:$K$135,"Info")),0) -> 0.25 | L36: =IFERROR((COUNTIF(Matrice!$L$131:$L$135,"Natif")+COUNTIF(Matrice!$L$131:$L$135,"Officiel"))/(C36-COUNTIF(Matrice!$L$131:$L$135,"Info")),0) -> 0.25 | M36: =IFERROR((COUNTIF(Matrice!$M$131:$M$135,"Natif")+COUNTIF(Matrice!$M$131:$M$135,"Officiel"))/(C36-COUNTIF(Matrice!$M$131:$M$135,"Info")),0) -> 0.25
A37: Technique | B37: Configuration as code | C37: 4 | D37: =IFERROR((COUNTIF(Matrice!$D$136:$D$139,"Natif")+COUNTIF(Matrice!$D$136:$D$139,"Officiel"))/(C37-COUNTIF(Matrice!$D$136:$D$139,"Info")),0) -> 0.5 | E37: =IFERROR((COUNTIF(Matrice!$E$136:$E$139,"Natif")+COUNTIF(Matrice!$E$136:$E$139,"Officiel"))/(C37-COUNTIF(Matrice!$E$136:$E$139,"Info")),0) -> 0.75 | F37: =IFERROR((COUNTIF(Matrice!$F$136:$F$139,"Natif")+COUNTIF(Matrice!$F$136:$F$139,"Officiel"))/(C37-COUNTIF(Matrice!$F$136:$F$139,"Info")),0) -> 1 | G37: =IFERROR((COUNTIF(Matrice!$G$136:$G$139,"Natif")+COUNTIF(Matrice!$G$136:$G$139,"Officiel"))/(C37-COUNTIF(Matrice!$G$136:$G$139,"Info")),0) -> 0.75 | H37: =IFERROR((COUNTIF(Matrice!$H$136:$H$139,"Natif")+COUNTIF(Matrice!$H$136:$H$139,"Officiel"))/(C37-COUNTIF(Matrice!$H$136:$H$139,"Info")),0) -> 1 | I37: =IFERROR((COUNTIF(Matrice!$I$136:$I$139,"Natif")+COUNTIF(Matrice!$I$136:$I$139,"Officiel"))/(C37-COUNTIF(Matrice!$I$136:$I$139,"Info")),0) -> 0.5 | J37: =IFERROR((COUNTIF(Matrice!$J$136:$J$139,"Natif")+COUNTIF(Matrice!$J$136:$J$139,"Officiel"))/(C37-COUNTIF(Matrice!$J$136:$J$139,"Info")),0) -> 1 | K37: =IFERROR((COUNTIF(Matrice!$K$136:$K$139,"Natif")+COUNTIF(Matrice!$K$136:$K$139,"Officiel"))/(C37-COUNTIF(Matrice!$K$136:$K$139,"Info")),0) -> 1 | L37: =IFERROR((COUNTIF(Matrice!$L$136:$L$139,"Natif")+COUNTIF(Matrice!$L$136:$L$139,"Officiel"))/(C37-COUNTIF(Matrice!$L$136:$L$139,"Info")),0) -> 0.25 | M37: =IFERROR((COUNTIF(Matrice!$M$136:$M$139,"Natif")+COUNTIF(Matrice!$M$136:$M$139,"Officiel"))/(C37-COUNTIF(Matrice!$M$136:$M$139,"Info")),0) -> 0.25
A38: Technique | B38: Synchronisation entre environnements | C38: 4 | D38: =IFERROR((COUNTIF(Matrice!$D$140:$D$143,"Natif")+COUNTIF(Matrice!$D$140:$D$143,"Officiel"))/(C38-COUNTIF(Matrice!$D$140:$D$143,"Info")),0) -> 0 | E38: =IFERROR((COUNTIF(Matrice!$E$140:$E$143,"Natif")+COUNTIF(Matrice!$E$140:$E$143,"Officiel"))/(C38-COUNTIF(Matrice!$E$140:$E$143,"Info")),0) -> 0.75 | F38: =IFERROR((COUNTIF(Matrice!$F$140:$F$143,"Natif")+COUNTIF(Matrice!$F$140:$F$143,"Officiel"))/(C38-COUNTIF(Matrice!$F$140:$F$143,"Info")),0) -> 0.5 | G38: =IFERROR((COUNTIF(Matrice!$G$140:$G$143,"Natif")+COUNTIF(Matrice!$G$140:$G$143,"Officiel"))/(C38-COUNTIF(Matrice!$G$140:$G$143,"Info")),0) -> 0.25 | H38: =IFERROR((COUNTIF(Matrice!$H$140:$H$143,"Natif")+COUNTIF(Matrice!$H$140:$H$143,"Officiel"))/(C38-COUNTIF(Matrice!$H$140:$H$143,"Info")),0) -> 0.75 | I38: =IFERROR((COUNTIF(Matrice!$I$140:$I$143,"Natif")+COUNTIF(Matrice!$I$140:$I$143,"Officiel"))/(C38-COUNTIF(Matrice!$I$140:$I$143,"Info")),0) -> 0.25 | J38: =IFERROR((COUNTIF(Matrice!$J$140:$J$143,"Natif")+COUNTIF(Matrice!$J$140:$J$143,"Officiel"))/(C38-COUNTIF(Matrice!$J$140:$J$143,"Info")),0) -> 0.5 | K38: =IFERROR((COUNTIF(Matrice!$K$140:$K$143,"Natif")+COUNTIF(Matrice!$K$140:$K$143,"Officiel"))/(C38-COUNTIF(Matrice!$K$140:$K$143,"Info")),0) -> 0.5 | L38: =IFERROR((COUNTIF(Matrice!$L$140:$L$143,"Natif")+COUNTIF(Matrice!$L$140:$L$143,"Officiel"))/(C38-COUNTIF(Matrice!$L$140:$L$143,"Info")),0) -> 0.25 | M38: =IFERROR((COUNTIF(Matrice!$M$140:$M$143,"Natif")+COUNTIF(Matrice!$M$140:$M$143,"Officiel"))/(C38-COUNTIF(Matrice!$M$140:$M$143,"Info")),0) -> 0
A39: Technique | B39: Extensibilité | C39: 7 | D39: =IFERROR((COUNTIF(Matrice!$D$144:$D$150,"Natif")+COUNTIF(Matrice!$D$144:$D$150,"Officiel"))/(C39-COUNTIF(Matrice!$D$144:$D$150,"Info")),0) -> 1 | E39: =IFERROR((COUNTIF(Matrice!$E$144:$E$150,"Natif")+COUNTIF(Matrice!$E$144:$E$150,"Officiel"))/(C39-COUNTIF(Matrice!$E$144:$E$150,"Info")),0) -> 1 | F39: =IFERROR((COUNTIF(Matrice!$F$144:$F$150,"Natif")+COUNTIF(Matrice!$F$144:$F$150,"Officiel"))/(C39-COUNTIF(Matrice!$F$144:$F$150,"Info")),0) -> 1 | G39: =IFERROR((COUNTIF(Matrice!$G$144:$G$150,"Natif")+COUNTIF(Matrice!$G$144:$G$150,"Officiel"))/(C39-COUNTIF(Matrice!$G$144:$G$150,"Info")),0) -> 0.85714286 | H39: =IFERROR((COUNTIF(Matrice!$H$144:$H$150,"Natif")+COUNTIF(Matrice!$H$144:$H$150,"Officiel"))/(C39-COUNTIF(Matrice!$H$144:$H$150,"Info")),0) -> 1 | I39: =IFERROR((COUNTIF(Matrice!$I$144:$I$150,"Natif")+COUNTIF(Matrice!$I$144:$I$150,"Officiel"))/(C39-COUNTIF(Matrice!$I$144:$I$150,"Info")),0) -> 1 | J39: =IFERROR((COUNTIF(Matrice!$J$144:$J$150,"Natif")+COUNTIF(Matrice!$J$144:$J$150,"Officiel"))/(C39-COUNTIF(Matrice!$J$144:$J$150,"Info")),0) -> 1 | K39: =IFERROR((COUNTIF(Matrice!$K$144:$K$150,"Natif")+COUNTIF(Matrice!$K$144:$K$150,"Officiel"))/(C39-COUNTIF(Matrice!$K$144:$K$150,"Info")),0) -> 0.85714286 | L39: =IFERROR((COUNTIF(Matrice!$L$144:$L$150,"Natif")+COUNTIF(Matrice!$L$144:$L$150,"Officiel"))/(C39-COUNTIF(Matrice!$L$144:$L$150,"Info")),0) -> 0.85714286 | M39: =IFERROR((COUNTIF(Matrice!$M$144:$M$150,"Natif")+COUNTIF(Matrice!$M$144:$M$150,"Officiel"))/(C39-COUNTIF(Matrice!$M$144:$M$150,"Info")),0) -> 0.85714286
A40: Technique | B40: Performance et cache | C40: 7 | D40: =IFERROR((COUNTIF(Matrice!$D$151:$D$157,"Natif")+COUNTIF(Matrice!$D$151:$D$157,"Officiel"))/(C40-COUNTIF(Matrice!$D$151:$D$157,"Info")),0) -> 1 | E40: =IFERROR((COUNTIF(Matrice!$E$151:$E$157,"Natif")+COUNTIF(Matrice!$E$151:$E$157,"Officiel"))/(C40-COUNTIF(Matrice!$E$151:$E$157,"Info")),0) -> 0.71428571 | F40: =IFERROR((COUNTIF(Matrice!$F$151:$F$157,"Natif")+COUNTIF(Matrice!$F$151:$F$157,"Officiel"))/(C40-COUNTIF(Matrice!$F$151:$F$157,"Info")),0) -> 0.42857143 | G40: =IFERROR((COUNTIF(Matrice!$G$151:$G$157,"Natif")+COUNTIF(Matrice!$G$151:$G$157,"Officiel"))/(C40-COUNTIF(Matrice!$G$151:$G$157,"Info")),0) -> 0.42857143 | H40: =IFERROR((COUNTIF(Matrice!$H$151:$H$157,"Natif")+COUNTIF(Matrice!$H$151:$H$157,"Officiel"))/(C40-COUNTIF(Matrice!$H$151:$H$157,"Info")),0) -> 0.71428571 | I40: =IFERROR((COUNTIF(Matrice!$I$151:$I$157,"Natif")+COUNTIF(Matrice!$I$151:$I$157,"Officiel"))/(C40-COUNTIF(Matrice!$I$151:$I$157,"Info")),0) -> 0.28571429 | J40: =IFERROR((COUNTIF(Matrice!$J$151:$J$157,"Natif")+COUNTIF(Matrice!$J$151:$J$157,"Officiel"))/(C40-COUNTIF(Matrice!$J$151:$J$157,"Info")),0) -> 0.71428571 | K40: =IFERROR((COUNTIF(Matrice!$K$151:$K$157,"Natif")+COUNTIF(Matrice!$K$151:$K$157,"Officiel"))/(C40-COUNTIF(Matrice!$K$151:$K$157,"Info")),0) -> 0.14285714 | L40: =IFERROR((COUNTIF(Matrice!$L$151:$L$157,"Natif")+COUNTIF(Matrice!$L$151:$L$157,"Officiel"))/(C40-COUNTIF(Matrice!$L$151:$L$157,"Info")),0) -> 0.28571429 | M40: =IFERROR((COUNTIF(Matrice!$M$151:$M$157,"Natif")+COUNTIF(Matrice!$M$151:$M$157,"Officiel"))/(C40-COUNTIF(Matrice!$M$151:$M$157,"Info")),0) -> 0.14285714
A41: Technique | B41: Tâches planifiées et files d'attente | C41: 3 | D41: =IFERROR((COUNTIF(Matrice!$D$158:$D$160,"Natif")+COUNTIF(Matrice!$D$158:$D$160,"Officiel"))/(C41-COUNTIF(Matrice!$D$158:$D$160,"Info")),0) -> 0.66666667 | E41: =IFERROR((COUNTIF(Matrice!$E$158:$E$160,"Natif")+COUNTIF(Matrice!$E$158:$E$160,"Officiel"))/(C41-COUNTIF(Matrice!$E$158:$E$160,"Info")),0) -> 1 | F41: =IFERROR((COUNTIF(Matrice!$F$158:$F$160,"Natif")+COUNTIF(Matrice!$F$158:$F$160,"Officiel"))/(C41-COUNTIF(Matrice!$F$158:$F$160,"Info")),0) -> 0.66666667 | G41: =IFERROR((COUNTIF(Matrice!$G$158:$G$160,"Natif")+COUNTIF(Matrice!$G$158:$G$160,"Officiel"))/(C41-COUNTIF(Matrice!$G$158:$G$160,"Info")),0) -> 0 | H41: =IFERROR((COUNTIF(Matrice!$H$158:$H$160,"Natif")+COUNTIF(Matrice!$H$158:$H$160,"Officiel"))/(C41-COUNTIF(Matrice!$H$158:$H$160,"Info")),0) -> 1 | I41: =IFERROR((COUNTIF(Matrice!$I$158:$I$160,"Natif")+COUNTIF(Matrice!$I$158:$I$160,"Officiel"))/(C41-COUNTIF(Matrice!$I$158:$I$160,"Info")),0) -> 0.66666667 | J41: =IFERROR((COUNTIF(Matrice!$J$158:$J$160,"Natif")+COUNTIF(Matrice!$J$158:$J$160,"Officiel"))/(C41-COUNTIF(Matrice!$J$158:$J$160,"Info")),0) -> 0.33333333 | K41: =IFERROR((COUNTIF(Matrice!$K$158:$K$160,"Natif")+COUNTIF(Matrice!$K$158:$K$160,"Officiel"))/(C41-COUNTIF(Matrice!$K$158:$K$160,"Info")),0) -> 1 | L41: =IFERROR((COUNTIF(Matrice!$L$158:$L$160,"Natif")+COUNTIF(Matrice!$L$158:$L$160,"Officiel"))/(C41-COUNTIF(Matrice!$L$158:$L$160,"Info")),0) -> 1 | M41: =IFERROR((COUNTIF(Matrice!$M$158:$M$160,"Natif")+COUNTIF(Matrice!$M$158:$M$160,"Officiel"))/(C41-COUNTIF(Matrice!$M$158:$M$160,"Info")),0) -> 0.66666667
A42: Technique | B42: Sécurité | C42: 7 | D42: =IFERROR((COUNTIF(Matrice!$D$161:$D$167,"Natif")+COUNTIF(Matrice!$D$161:$D$167,"Officiel"))/(C42-COUNTIF(Matrice!$D$161:$D$167,"Info")),0) -> 0.71428571 | E42: =IFERROR((COUNTIF(Matrice!$E$161:$E$167,"Natif")+COUNTIF(Matrice!$E$161:$E$167,"Officiel"))/(C42-COUNTIF(Matrice!$E$161:$E$167,"Info")),0) -> 0.57142857 | F42: =IFERROR((COUNTIF(Matrice!$F$161:$F$167,"Natif")+COUNTIF(Matrice!$F$161:$F$167,"Officiel"))/(C42-COUNTIF(Matrice!$F$161:$F$167,"Info")),0) -> 0.57142857 | G42: =IFERROR((COUNTIF(Matrice!$G$161:$G$167,"Natif")+COUNTIF(Matrice!$G$161:$G$167,"Officiel"))/(C42-COUNTIF(Matrice!$G$161:$G$167,"Info")),0) -> 0.57142857 | H42: =IFERROR((COUNTIF(Matrice!$H$161:$H$167,"Natif")+COUNTIF(Matrice!$H$161:$H$167,"Officiel"))/(C42-COUNTIF(Matrice!$H$161:$H$167,"Info")),0) -> 0.71428571 | I42: =IFERROR((COUNTIF(Matrice!$I$161:$I$167,"Natif")+COUNTIF(Matrice!$I$161:$I$167,"Officiel"))/(C42-COUNTIF(Matrice!$I$161:$I$167,"Info")),0) -> 0.71428571 | J42: =IFERROR((COUNTIF(Matrice!$J$161:$J$167,"Natif")+COUNTIF(Matrice!$J$161:$J$167,"Officiel"))/(C42-COUNTIF(Matrice!$J$161:$J$167,"Info")),0) -> 0.71428571 | K42: =IFERROR((COUNTIF(Matrice!$K$161:$K$167,"Natif")+COUNTIF(Matrice!$K$161:$K$167,"Officiel"))/(C42-COUNTIF(Matrice!$K$161:$K$167,"Info")),0) -> 0.57142857 | L42: =IFERROR((COUNTIF(Matrice!$L$161:$L$167,"Natif")+COUNTIF(Matrice!$L$161:$L$167,"Officiel"))/(C42-COUNTIF(Matrice!$L$161:$L$167,"Info")),0) -> 0.42857143 | M42: =IFERROR((COUNTIF(Matrice!$M$161:$M$167,"Natif")+COUNTIF(Matrice!$M$161:$M$167,"Officiel"))/(C42-COUNTIF(Matrice!$M$161:$M$167,"Info")),0) -> 0.28571429
A43: Technique | B43: Outils développeur | C43: 8 | D43: =IFERROR((COUNTIF(Matrice!$D$168:$D$175,"Natif")+COUNTIF(Matrice!$D$168:$D$175,"Officiel"))/(C43-COUNTIF(Matrice!$D$168:$D$175,"Info")),0) -> 0.5 | E43: =IFERROR((COUNTIF(Matrice!$E$168:$E$175,"Natif")+COUNTIF(Matrice!$E$168:$E$175,"Officiel"))/(C43-COUNTIF(Matrice!$E$168:$E$175,"Info")),0) -> 0.5 | F43: =IFERROR((COUNTIF(Matrice!$F$168:$F$175,"Natif")+COUNTIF(Matrice!$F$168:$F$175,"Officiel"))/(C43-COUNTIF(Matrice!$F$168:$F$175,"Info")),0) -> 0.75 | G43: =IFERROR((COUNTIF(Matrice!$G$168:$G$175,"Natif")+COUNTIF(Matrice!$G$168:$G$175,"Officiel"))/(C43-COUNTIF(Matrice!$G$168:$G$175,"Info")),0) -> 0.5 | H43: =IFERROR((COUNTIF(Matrice!$H$168:$H$175,"Natif")+COUNTIF(Matrice!$H$168:$H$175,"Officiel"))/(C43-COUNTIF(Matrice!$H$168:$H$175,"Info")),0) -> 0.75 | I43: =IFERROR((COUNTIF(Matrice!$I$168:$I$175,"Natif")+COUNTIF(Matrice!$I$168:$I$175,"Officiel"))/(C43-COUNTIF(Matrice!$I$168:$I$175,"Info")),0) -> 0.875 | J43: =IFERROR((COUNTIF(Matrice!$J$168:$J$175,"Natif")+COUNTIF(Matrice!$J$168:$J$175,"Officiel"))/(C43-COUNTIF(Matrice!$J$168:$J$175,"Info")),0) -> 0.5 | K43: =IFERROR((COUNTIF(Matrice!$K$168:$K$175,"Natif")+COUNTIF(Matrice!$K$168:$K$175,"Officiel"))/(C43-COUNTIF(Matrice!$K$168:$K$175,"Info")),0) -> 0.5 | L43: =IFERROR((COUNTIF(Matrice!$L$168:$L$175,"Natif")+COUNTIF(Matrice!$L$168:$L$175,"Officiel"))/(C43-COUNTIF(Matrice!$L$168:$L$175,"Info")),0) -> 0.5 | M43: =IFERROR((COUNTIF(Matrice!$M$168:$M$175,"Natif")+COUNTIF(Matrice!$M$168:$M$175,"Officiel"))/(C43-COUNTIF(Matrice!$M$168:$M$175,"Info")),0) -> 0.375
A44: Technique | B44: Installation et mises à jour | C44: 6 | D44: =IFERROR((COUNTIF(Matrice!$D$176:$D$181,"Natif")+COUNTIF(Matrice!$D$176:$D$181,"Officiel"))/(C44-COUNTIF(Matrice!$D$176:$D$181,"Info")),0) -> 0.83333333 | E44: =IFERROR((COUNTIF(Matrice!$E$176:$E$181,"Natif")+COUNTIF(Matrice!$E$176:$E$181,"Officiel"))/(C44-COUNTIF(Matrice!$E$176:$E$181,"Info")),0) -> 0.66666667 | F44: =IFERROR((COUNTIF(Matrice!$F$176:$F$181,"Natif")+COUNTIF(Matrice!$F$176:$F$181,"Officiel"))/(C44-COUNTIF(Matrice!$F$176:$F$181,"Info")),0) -> 0.5 | G44: =IFERROR((COUNTIF(Matrice!$G$176:$G$181,"Natif")+COUNTIF(Matrice!$G$176:$G$181,"Officiel"))/(C44-COUNTIF(Matrice!$G$176:$G$181,"Info")),0) -> 0.5 | H44: =IFERROR((COUNTIF(Matrice!$H$176:$H$181,"Natif")+COUNTIF(Matrice!$H$176:$H$181,"Officiel"))/(C44-COUNTIF(Matrice!$H$176:$H$181,"Info")),0) -> 0.33333333 | I44: =IFERROR((COUNTIF(Matrice!$I$176:$I$181,"Natif")+COUNTIF(Matrice!$I$176:$I$181,"Officiel"))/(C44-COUNTIF(Matrice!$I$176:$I$181,"Info")),0) -> 0.66666667 | J44: =IFERROR((COUNTIF(Matrice!$J$176:$J$181,"Natif")+COUNTIF(Matrice!$J$176:$J$181,"Officiel"))/(C44-COUNTIF(Matrice!$J$176:$J$181,"Info")),0) -> 0.66666667 | K44: =IFERROR((COUNTIF(Matrice!$K$176:$K$181,"Natif")+COUNTIF(Matrice!$K$176:$K$181,"Officiel"))/(C44-COUNTIF(Matrice!$K$176:$K$181,"Info")),0) -> 0.16666667 | L44: =IFERROR((COUNTIF(Matrice!$L$176:$L$181,"Natif")+COUNTIF(Matrice!$L$176:$L$181,"Officiel"))/(C44-COUNTIF(Matrice!$L$176:$L$181,"Info")),0) -> 0.66666667 | M44: =IFERROR((COUNTIF(Matrice!$M$176:$M$181,"Natif")+COUNTIF(Matrice!$M$176:$M$181,"Officiel"))/(C44-COUNTIF(Matrice!$M$176:$M$181,"Info")),0) -> 0.33333333
A45: Technique | B45: IA | C45: 5 | D45: =IFERROR((COUNTIF(Matrice!$D$182:$D$186,"Natif")+COUNTIF(Matrice!$D$182:$D$186,"Officiel"))/(C45-COUNTIF(Matrice!$D$182:$D$186,"Info")),0) -> 0.8 | E45: =IFERROR((COUNTIF(Matrice!$E$182:$E$186,"Natif")+COUNTIF(Matrice!$E$182:$E$186,"Officiel"))/(C45-COUNTIF(Matrice!$E$182:$E$186,"Info")),0) -> 0 | F45: =IFERROR((COUNTIF(Matrice!$F$182:$F$186,"Natif")+COUNTIF(Matrice!$F$182:$F$186,"Officiel"))/(C45-COUNTIF(Matrice!$F$182:$F$186,"Info")),0) -> 0 | G45: =IFERROR((COUNTIF(Matrice!$G$182:$G$186,"Natif")+COUNTIF(Matrice!$G$182:$G$186,"Officiel"))/(C45-COUNTIF(Matrice!$G$182:$G$186,"Info")),0) -> 0 | H45: =IFERROR((COUNTIF(Matrice!$H$182:$H$186,"Natif")+COUNTIF(Matrice!$H$182:$H$186,"Officiel"))/(C45-COUNTIF(Matrice!$H$182:$H$186,"Info")),0) -> 0 | I45: =IFERROR((COUNTIF(Matrice!$I$182:$I$186,"Natif")+COUNTIF(Matrice!$I$182:$I$186,"Officiel"))/(C45-COUNTIF(Matrice!$I$182:$I$186,"Info")),0) -> 0.2 | J45: =IFERROR((COUNTIF(Matrice!$J$182:$J$186,"Natif")+COUNTIF(Matrice!$J$182:$J$186,"Officiel"))/(C45-COUNTIF(Matrice!$J$182:$J$186,"Info")),0) -> 0.8 | K45: =IFERROR((COUNTIF(Matrice!$K$182:$K$186,"Natif")+COUNTIF(Matrice!$K$182:$K$186,"Officiel"))/(C45-COUNTIF(Matrice!$K$182:$K$186,"Info")),0) -> 0.8 | L45: =IFERROR((COUNTIF(Matrice!$L$182:$L$186,"Natif")+COUNTIF(Matrice!$L$182:$L$186,"Officiel"))/(C45-COUNTIF(Matrice!$L$182:$L$186,"Info")),0) -> 0 | M45: =IFERROR((COUNTIF(Matrice!$M$182:$M$186,"Natif")+COUNTIF(Matrice!$M$182:$M$186,"Officiel"))/(C45-COUNTIF(Matrice!$M$182:$M$186,"Info")),0) -> 0
A46: Gouvernance | B46: Conformité et vie privée | C46: 5 | D46: =IFERROR((COUNTIF(Matrice!$D$187:$D$191,"Natif")+COUNTIF(Matrice!$D$187:$D$191,"Officiel"))/(C46-COUNTIF(Matrice!$D$187:$D$191,"Info")),0) -> 0.6 | E46: =IFERROR((COUNTIF(Matrice!$E$187:$E$191,"Natif")+COUNTIF(Matrice!$E$187:$E$191,"Officiel"))/(C46-COUNTIF(Matrice!$E$187:$E$191,"Info")),0) -> 0 | F46: =IFERROR((COUNTIF(Matrice!$F$187:$F$191,"Natif")+COUNTIF(Matrice!$F$187:$F$191,"Officiel"))/(C46-COUNTIF(Matrice!$F$187:$F$191,"Info")),0) -> 0 | G46: =IFERROR((COUNTIF(Matrice!$G$187:$G$191,"Natif")+COUNTIF(Matrice!$G$187:$G$191,"Officiel"))/(C46-COUNTIF(Matrice!$G$187:$G$191,"Info")),0) -> 0 | H46: =IFERROR((COUNTIF(Matrice!$H$187:$H$191,"Natif")+COUNTIF(Matrice!$H$187:$H$191,"Officiel"))/(C46-COUNTIF(Matrice!$H$187:$H$191,"Info")),0) -> 0 | I46: =IFERROR((COUNTIF(Matrice!$I$187:$I$191,"Natif")+COUNTIF(Matrice!$I$187:$I$191,"Officiel"))/(C46-COUNTIF(Matrice!$I$187:$I$191,"Info")),0) -> 0 | J46: =IFERROR((COUNTIF(Matrice!$J$187:$J$191,"Natif")+COUNTIF(Matrice!$J$187:$J$191,"Officiel"))/(C46-COUNTIF(Matrice!$J$187:$J$191,"Info")),0) -> 0 | K46: =IFERROR((COUNTIF(Matrice!$K$187:$K$191,"Natif")+COUNTIF(Matrice!$K$187:$K$191,"Officiel"))/(C46-COUNTIF(Matrice!$K$187:$K$191,"Info")),0) -> 0 | L46: =IFERROR((COUNTIF(Matrice!$L$187:$L$191,"Natif")+COUNTIF(Matrice!$L$187:$L$191,"Officiel"))/(C46-COUNTIF(Matrice!$L$187:$L$191,"Info")),0) -> 0 | M46: =IFERROR((COUNTIF(Matrice!$M$187:$M$191,"Natif")+COUNTIF(Matrice!$M$187:$M$191,"Officiel"))/(C46-COUNTIF(Matrice!$M$187:$M$191,"Info")),0) -> 0
A47: Gouvernance | B47: Analytics et tableau de bord | C47: 4 | D47: =IFERROR((COUNTIF(Matrice!$D$192:$D$195,"Natif")+COUNTIF(Matrice!$D$192:$D$195,"Officiel"))/(C47-COUNTIF(Matrice!$D$192:$D$195,"Info")),0) -> 0.5 | E47: =IFERROR((COUNTIF(Matrice!$E$192:$E$195,"Natif")+COUNTIF(Matrice!$E$192:$E$195,"Officiel"))/(C47-COUNTIF(Matrice!$E$192:$E$195,"Info")),0) -> 0.25 | F47: =IFERROR((COUNTIF(Matrice!$F$192:$F$195,"Natif")+COUNTIF(Matrice!$F$192:$F$195,"Officiel"))/(C47-COUNTIF(Matrice!$F$192:$F$195,"Info")),0) -> 0.25 | G47: =IFERROR((COUNTIF(Matrice!$G$192:$G$195,"Natif")+COUNTIF(Matrice!$G$192:$G$195,"Officiel"))/(C47-COUNTIF(Matrice!$G$192:$G$195,"Info")),0) -> 0 | H47: =IFERROR((COUNTIF(Matrice!$H$192:$H$195,"Natif")+COUNTIF(Matrice!$H$192:$H$195,"Officiel"))/(C47-COUNTIF(Matrice!$H$192:$H$195,"Info")),0) -> 0.5 | I47: =IFERROR((COUNTIF(Matrice!$I$192:$I$195,"Natif")+COUNTIF(Matrice!$I$192:$I$195,"Officiel"))/(C47-COUNTIF(Matrice!$I$192:$I$195,"Info")),0) -> 0.75 | J47: =IFERROR((COUNTIF(Matrice!$J$192:$J$195,"Natif")+COUNTIF(Matrice!$J$192:$J$195,"Officiel"))/(C47-COUNTIF(Matrice!$J$192:$J$195,"Info")),0) -> 0.5 | K47: =IFERROR((COUNTIF(Matrice!$K$192:$K$195,"Natif")+COUNTIF(Matrice!$K$192:$K$195,"Officiel"))/(C47-COUNTIF(Matrice!$K$192:$K$195,"Info")),0) -> 0.25 | L47: =IFERROR((COUNTIF(Matrice!$L$192:$L$195,"Natif")+COUNTIF(Matrice!$L$192:$L$195,"Officiel"))/(C47-COUNTIF(Matrice!$L$192:$L$195,"Info")),0) -> 0.75 | M47: =IFERROR((COUNTIF(Matrice!$M$192:$M$195,"Natif")+COUNTIF(Matrice!$M$192:$M$195,"Officiel"))/(C47-COUNTIF(Matrice!$M$192:$M$195,"Info")),0) -> 0.25
A48: Gouvernance | B48: Interface d'administration | C48: 9 | D48: =IFERROR((COUNTIF(Matrice!$D$196:$D$204,"Natif")+COUNTIF(Matrice!$D$196:$D$204,"Officiel"))/(C48-COUNTIF(Matrice!$D$196:$D$204,"Info")),0) -> 0.55555556 | E48: =IFERROR((COUNTIF(Matrice!$E$196:$E$204,"Natif")+COUNTIF(Matrice!$E$196:$E$204,"Officiel"))/(C48-COUNTIF(Matrice!$E$196:$E$204,"Info")),0) -> 0.44444444 | F48: =IFERROR((COUNTIF(Matrice!$F$196:$F$204,"Natif")+COUNTIF(Matrice!$F$196:$F$204,"Officiel"))/(C48-COUNTIF(Matrice!$F$196:$F$204,"Info")),0) -> 0.66666667 | G48: =IFERROR((COUNTIF(Matrice!$G$196:$G$204,"Natif")+COUNTIF(Matrice!$G$196:$G$204,"Officiel"))/(C48-COUNTIF(Matrice!$G$196:$G$204,"Info")),0) -> 0.55555556 | H48: =IFERROR((COUNTIF(Matrice!$H$196:$H$204,"Natif")+COUNTIF(Matrice!$H$196:$H$204,"Officiel"))/(C48-COUNTIF(Matrice!$H$196:$H$204,"Info")),0) -> 1 | I48: =IFERROR((COUNTIF(Matrice!$I$196:$I$204,"Natif")+COUNTIF(Matrice!$I$196:$I$204,"Officiel"))/(C48-COUNTIF(Matrice!$I$196:$I$204,"Info")),0) -> 0.77777778 | J48: =IFERROR((COUNTIF(Matrice!$J$196:$J$204,"Natif")+COUNTIF(Matrice!$J$196:$J$204,"Officiel"))/(C48-COUNTIF(Matrice!$J$196:$J$204,"Info")),0) -> 0.66666667 | K48: =IFERROR((COUNTIF(Matrice!$K$196:$K$204,"Natif")+COUNTIF(Matrice!$K$196:$K$204,"Officiel"))/(C48-COUNTIF(Matrice!$K$196:$K$204,"Info")),0) -> 0.77777778 | L48: =IFERROR((COUNTIF(Matrice!$L$196:$L$204,"Natif")+COUNTIF(Matrice!$L$196:$L$204,"Officiel"))/(C48-COUNTIF(Matrice!$L$196:$L$204,"Info")),0) -> 0.44444444 | M48: =IFERROR((COUNTIF(Matrice!$M$196:$M$204,"Natif")+COUNTIF(Matrice!$M$196:$M$204,"Officiel"))/(C48-COUNTIF(Matrice!$M$196:$M$204,"Info")),0) -> 0.66666667
A49: Gouvernance | B49: Écosystème et communauté | C49: 8 | D49: =IFERROR((COUNTIF(Matrice!$D$205:$D$212,"Natif")+COUNTIF(Matrice!$D$205:$D$212,"Officiel"))/(C49-COUNTIF(Matrice!$D$205:$D$212,"Info")),0) -> 0 | E49: =IFERROR((COUNTIF(Matrice!$E$205:$E$212,"Natif")+COUNTIF(Matrice!$E$205:$E$212,"Officiel"))/(C49-COUNTIF(Matrice!$E$205:$E$212,"Info")),0) -> 0 | F49: =IFERROR((COUNTIF(Matrice!$F$205:$F$212,"Natif")+COUNTIF(Matrice!$F$205:$F$212,"Officiel"))/(C49-COUNTIF(Matrice!$F$205:$F$212,"Info")),0) -> 0 | G49: =IFERROR((COUNTIF(Matrice!$G$205:$G$212,"Natif")+COUNTIF(Matrice!$G$205:$G$212,"Officiel"))/(C49-COUNTIF(Matrice!$G$205:$G$212,"Info")),0) -> 0 | H49: =IFERROR((COUNTIF(Matrice!$H$205:$H$212,"Natif")+COUNTIF(Matrice!$H$205:$H$212,"Officiel"))/(C49-COUNTIF(Matrice!$H$205:$H$212,"Info")),0) -> 0 | I49: =IFERROR((COUNTIF(Matrice!$I$205:$I$212,"Natif")+COUNTIF(Matrice!$I$205:$I$212,"Officiel"))/(C49-COUNTIF(Matrice!$I$205:$I$212,"Info")),0) -> 0 | J49: =IFERROR((COUNTIF(Matrice!$J$205:$J$212,"Natif")+COUNTIF(Matrice!$J$205:$J$212,"Officiel"))/(C49-COUNTIF(Matrice!$J$205:$J$212,"Info")),0) -> 0 | K49: =IFERROR((COUNTIF(Matrice!$K$205:$K$212,"Natif")+COUNTIF(Matrice!$K$205:$K$212,"Officiel"))/(C49-COUNTIF(Matrice!$K$205:$K$212,"Info")),0) -> 0 | L49: =IFERROR((COUNTIF(Matrice!$L$205:$L$212,"Natif")+COUNTIF(Matrice!$L$205:$L$212,"Officiel"))/(C49-COUNTIF(Matrice!$L$205:$L$212,"Info")),0) -> 0 | M49: =IFERROR((COUNTIF(Matrice!$M$205:$M$212,"Natif")+COUNTIF(Matrice!$M$205:$M$212,"Officiel"))/(C49-COUNTIF(Matrice!$M$205:$M$212,"Info")),0) -> 0

Sheet Priorisation
A1: Priorisation pour un CMS Laravel / Filament
A2: Proposition à valider. MVP = socle indispensable au lancement ; V1 = attendu par le marché ; V2 = plus tard ; Hors périmètre = écarté volontairement. Différenciant = peu couvert nativement par les 10 CMS et à forte valeur. « Couverture » = nombre de CMS sur 10 qui l'offrent en natif ou via extension officielle (formule vers la Matrice).
A4: Priorité | B4: Nb fonct. | C4: dont différenciantes
A5: MVP | B5: =COUNTIF($F$12:$F$2000,A5) -> 109 | C5: =COUNTIFS($F$12:$F$2000,A5,$G$12:$G$2000,"Oui") -> 17
A6: V1 | B6: =COUNTIF($F$12:$F$2000,A6) -> 123 | C6: =COUNTIFS($F$12:$F$2000,A6,$G$12:$G$2000,"Oui") -> 37
A7: V2 | B7: =COUNTIF($F$12:$F$2000,A7) -> 75 | C7: =COUNTIFS($F$12:$F$2000,A7,$G$12:$G$2000,"Oui") -> 25
A8: Hors périmètre | B8: =COUNTIF($F$12:$F$2000,A8) -> 26 | C8: =COUNTIFS($F$12:$F$2000,A8,$G$12:$G$2000,"Oui") -> 0
A9: Total | B9: =SUM(B5:B8) -> 333 | C9: =SUM(C5:C8) -> 79
A11: Bloc | B11: Catégorie | C11: Fonctionnalité | D11: Origine | E11: Couverture (/10) | F11: Priorité | G11: Différenciant | H11: Brique Laravel / Filament | I11: Vu chez (ajouts)
A12: Contenu | B12: Modélisation de contenu | C12: Types de contenu personnalisés (sans code) | D12: Grille | E12: =Matrice!O2 -> 4 | F12: V2 | H12: Générateur de schéma dans l'admin
A13: Contenu | B13: Modélisation de contenu | C13: Types de contenu définis en code (schéma versionnable) | D13: Grille | E13: =Matrice!O3 -> 8 | F13: MVP | H13: Classes PHP + migrations
A14: Contenu | B14: Modélisation de contenu | C14: Champs personnalisés (bibliothèque de types de champs) | D14: Grille | E14: =Matrice!O4 -> 8 | F14: MVP | H14: Champs Filament Forms
A15: Contenu | B15: Modélisation de contenu | C15: Champs répétables / groupes de champs | D15: Grille | E15: =Matrice!O5 -> 7 | F15: MVP | H15: Filament Repeater
A16: Contenu | B16: Modélisation de contenu | C16: Relations entre contenus (1-n, n-n) | D16: Grille | E16: =Matrice!O6 -> 7 | F16: MVP | H16: Relations Eloquent + Filament Select/RelationManager
A17: Contenu | B17: Modélisation de contenu | C17: Relations bidirectionnelles / reverse lookup | D17: Grille | E17: =Matrice!O7 -> 3 | F17: V1 | G17: Oui | H17: Relations inverses Eloquent
A18: Contenu | B18: Modélisation de contenu | C18: Taxonomies (catégories, tags, vocabulaires personnalisés) | D18: Grille | E18: =Matrice!O8 -> 6 | F18: MVP | H18: spatie/laravel-tags ou modèles dédiés
A19: Contenu | B19: Modélisation de contenu | C19: Contenu hiérarchique (arborescence parent/enfant) | D19: Grille | E19: =Matrice!O9 -> 9 | F19: MVP | H19: kalnoy/nestedset ou adjacency list
A20: Contenu | B20: Modélisation de contenu | C20: Ensembles de champs réutilisables (fieldsets / blueprints) | D20: Grille | E20: =Matrice!O10 -> 7 | F20: MVP | H20: Méthodes de schéma Filament réutilisables
A21: Contenu | B21: Modélisation de contenu | C21: Contenus globaux / singletons (réglages de site) | D21: Grille | E21: =Matrice!O11 -> 8 | F21: MVP | H21: spatie/laravel-settings + Filament Settings
A22: Contenu | B22: Modélisation de contenu | C22: Validation des champs (règles, champs obligatoires) | D22: Grille | E22: =Matrice!O12 -> 10 | F22: MVP | H22: Validation Laravel (natif Filament)
A23: Contenu | B23: Modélisation de contenu | C23: Champs conditionnels (affichage selon valeur) | D23: Grille | E23: =Matrice!O13 -> 6 | F23: MVP | H23: Filament visible() / live() (natif)
A24: Contenu | B24: Modélisation de contenu | C24: Champs calculés / dérivés | D24: Grille | E24: =Matrice!O14 -> 3 | F24: V1 | H24: Filament afterStateUpdated / accessors Eloquent
A25: Contenu | B25: Modélisation de contenu | C25: Constructeur de listes / requêtes sans code (pages, blocs, flux) | D25: Ajout (hors grille) | F25: V2 | G25: Oui | H25: Filament Table + query builder | I25: Drupal (Views), WordPress (Query Loop)
A26: Contenu | B26: Modélisation de contenu | C26: Cascade d'héritage des données et valeurs par défaut (globales → section → entrée) | D26: Ajout (hors grille) | F26: V1 | H26: Logique applicative | I26: Statamic, TallCMS
A27: Contenu | B27: Modélisation de contenu | C27: Format de titre automatique / titres générés | D27: Ajout (hors grille) | F27: V1 | H27: Mutators Eloquent | I27: Craft, Statamic
A28: Contenu | B28: Modélisation de contenu | C28: Dictionnaires : listes d'options issues de sources externes | D28: Ajout (hors grille) | F28: V2 | H28: Filament Select options() | I28: Statamic
A29: Contenu | B29: Modélisation de contenu | C29: Contenu virtuel issu de sources externes (API, autre base) | D29: Ajout (hors grille) | F29: V2 | H29: Eloquent / Sushi | I29: Kirby
A30: Contenu | B30: Modélisation de contenu | C30: UUID et liens internes stables (résistent aux renommages) | D30: Ajout (hors grille) | F30: MVP | H30: HasUuids Eloquent | I30: Kirby, Craft
A31: Contenu | B31: Modélisation de contenu | C31: Modes d'affichage multiples par type (carte, liste, complet) | D31: Ajout (hors grille) | F31: V1 | H31: Vues Blade par mode | I31: Drupal
A32: Contenu | B32: Modélisation de contenu | C32: Champs spécialisés : adresse, lien multi-type, couleur, icône, montant, JSON/code | D32: Ajout (hors grille) | F32: V1 | H32: Champs Filament + plugins | I32: Craft, Payload, Kirby
A33: Contenu | B33: Modélisation de contenu | C33: Champs de géolocalisation avec requêtes de proximité | D33: Ajout (hors grille) | F33: V2 | H33: Plugin carte Filament + requêtes spatiales | I33: Payload, Drupal (contrib)
A34: Contenu | B34: Modélisation de contenu | C34: Champs de mise en page (onglets, sections, colonnes) | D34: Ajout (hors grille) | F34: MVP | H34: Filament Tabs / Section / Grid (natif) | I34: Payload, Statamic
A35: Contenu | B35: Modélisation de contenu | C35: Ordre manuel par glisser-déposer | D35: Ajout (hors grille) | F35: MVP | H35: Filament reorderable() + eloquent-sortable | I35: Payload, Statamic
A36: Contenu | B36: Modélisation de contenu | C36: Plusieurs types d'entrée dans une même section | D36: Ajout (hors grille) | F36: V1 | H36: Single table + type | I36: Craft, October
A37: Contenu | B37: Modélisation de contenu | C37: Classe PHP dédiée par type de contenu (méthodes métier) | D37: Ajout (hors grille) | F37: MVP | H37: Modèles Eloquent | I37: Kirby, Drupal
... A39: Contenu | B39: Modélisation de contenu | C39: Outils de refactor de schéma (fusion, nettoyage, réenregistrement en masse) | D39: Ajout (hors grille) | F39: V2 | H39: Commandes Artisan | I39: Craft, October
A40: Contenu | B40: Édition et blocs | C40: Éditeur WYSIWYG / rich text | D40: Grille | E40: =Matrice!O15 -> 10 | F40: MVP | H40: Filament RichEditor (TipTap)
A41: Contenu | B41: Édition et blocs | C41: Éditeur par blocs (block editor / page builder) | D41: Grille | E41: =Matrice!O16 -> 8 | F41: MVP | H41: Filament Builder
A42: Contenu | B42: Édition et blocs | C42: Blocs personnalisés définis par le développeur | D42: Grille | E42: =Matrice!O17 -> 9 | F42: MVP | H42: Filament Builder\Block
A43: Contenu | B43: Édition et blocs | C43: Blocs imbriqués | D43: Grille | E43: =Matrice!O18 -> 7 | F43: V1 | H43: Builder dans Builder
A44: Contenu | B44: Édition et blocs | C44: Blocs / patterns réutilisables (synchronisés) | D44: Grille | E44: =Matrice!O19 -> 3 | F44: V1 | G44: Oui | H44: Modèle « bloc global » référencé
A45: Contenu | B45: Édition et blocs | C45: Support Markdown | D45: Grille | E45: =Matrice!O20 -> 6 | F45: V1 | H45: Filament MarkdownEditor + league/commonmark
A46: Contenu | B46: Édition et blocs | C46: Édition en contexte (front-end) | D46: Grille | E46: =Matrice!O21 -> 3 | F46: V2 | G46: Oui | H46: Livewire sur le front
A47: Contenu | B47: Édition et blocs | C47: Live preview / aperçu avant publication | D47: Grille | E47: =Matrice!O22 -> 9 | F47: MVP | H47: Plugin preview Filament / iframe signée
A48: Contenu | B48: Édition et blocs | C48: Aperçu responsive (mobile/tablette) | D48: Grille | E48: =Matrice!O23 -> 5 | F48: V1 | H48: Iframe redimensionnable
A49: Contenu | B49: Édition et blocs | C49: Raccourcis clavier / slash commands | D49: Grille | E49: =Matrice!O24 -> 4 | F49: V2 | H49: Extensions TipTap
A50: Contenu | B50: Édition et blocs | C50: Sauvegarde automatique des brouillons | D50: Grille | E50: =Matrice!O25 -> 6 | F50: V1 | H50: Livewire + autosave
A51: Contenu | B51: Édition et blocs | C51: Verrouillage de blocs / mode d'édition restreint au contenu | D51: Ajout (hors grille) | F51: V1 | G51: Oui | H51: Permissions par bloc | I51: WordPress
A52: Contenu | B52: Édition et blocs | C52: Visibilité des blocs par appareil ou par condition | D52: Ajout (hors grille) | F52: V1 | H52: Réglages communs aux blocs | I52: WordPress, TallCMS
A53: Contenu | B53: Édition et blocs | C53: Liaison de blocs à des champs ou sources de données | D53: Ajout (hors grille) | F53: V2 | H53: Logique applicative | I53: WordPress (Block Bindings)
A54: Contenu | B54: Édition et blocs | C54: Surcharge locale de blocs réutilisables | D54: Ajout (hors grille) | F54: V2 | H54: Logique applicative | I54: WordPress (Pattern Overrides)
A55: Contenu | B55: Édition et blocs | C55: Panneau de structure des blocs avec réordonnancement | D55: Ajout (hors grille) | F55: V1 | H55: Filament Builder collapsible / reorderable | I55: TallCMS
A56: Contenu | B56: Édition et blocs | C56: Sélecteur de blocs avec aperçus visuels, recherche et récents | D56: Ajout (hors grille) | F56: V1 | H56: Filament Builder blockPreviews / blockPickerColumns | I56: Statamic, TallCMS
A57: Contenu | B57: Édition et blocs | C57: Copier / coller de blocs et d'entrées entre champs | D57: Ajout (hors grille) | F57: V1 | H57: Filament Builder cloneable + presse-papiers | I57: Craft
A58: Contenu | B58: Édition et blocs | C58: Tokens dynamiques dans le contenu (merge tags, shortcodes) | D58: Ajout (hors grille) | F58: V1 | H58: Parseur de contenu | I58: TallCMS, WordPress, Grav, Kirby, Drupal
A59: Contenu | B59: Édition et blocs | C59: Sélecteur de liens internes (pages et entrées) | D59: Ajout (hors grille) | F59: MVP | H59: Champ lien personnalisé | I59: October, Craft, Kirby
A60: Contenu | B60: Édition et blocs | C60: Temps de lecture et nombre de mots | D60: Ajout (hors grille) | F60: V2 | H60: Helper | I60: Statamic, TallCMS
A61: Contenu | B61: Édition et blocs | C61: Vue calendrier des contenus programmés | D61: Ajout (hors grille) | F61: V2 | H61: Plugin calendrier Filament | I61: Statamic
A62: Contenu | B62: Édition et blocs | C62: Barre d'administration sur le front-end | D62: Ajout (hors grille) | F62: V1 | H62: Composant Blade conditionnel | I62: WordPress, Payload
A63: Contenu | B63: Édition et blocs | C63: Copie d'un contenu vers une autre langue | D63: Ajout (hors grille) | F63: V1 | H63: Action Filament | I63: Payload
A64: Contenu | B64: Édition et blocs | C64: Édition en panneau latéral et édition inline dans les listes | D64: Ajout (hors grille) | F64: V1 | H64: Filament slideOver / colonnes éditables (natif) | I64: Craft
A65: Contenu | B65: Édition et blocs | C65: Composants front codés et éditables dans le navigateur | D65: Ajout (hors grille) | F65: Hors périmètre | I65: Drupal (Canvas)
A66: Contenu | B66: Médias | C66: Médiathèque centralisée | D66: Grille | E66: =Matrice!O26 -> 8 | F66: MVP | H66: spatie/laravel-medialibrary + Curator
A67: Contenu | B67: Médias | C67: Dossiers / organisation des médias | D67: Grille | E67: =Matrice!O27 -> 5 | F67: V1 | H67: Plugin médiathèque Filament
A68: Contenu | B68: Médias | C68: Recadrage / point focal | D68: Grille | E68: =Matrice!O28 -> 4 | F68: V1 | H68: Filament imageEditor + point focal
A69: Contenu | B69: Médias | C69: Transformations d'images à la volée (tailles, formats) | D69: Grille | E69: =Matrice!O29 -> 6 | F69: MVP | H69: Génération à la première demande (Glide), sans queue
A70: Contenu | B70: Médias | C70: Conversion WebP/AVIF | D70: Grille | E70: =Matrice!O30 -> 7 | F70: MVP | H70: Conversions medialibrary (AVIF selon GD/Imagick dispo)
A71: Contenu | B71: Médias | C71: Métadonnées des médias (alt, légende, crédits) | D71: Grille | E71: =Matrice!O31 -> 7 | F71: MVP | H71: Custom properties medialibrary
A72: Contenu | B72: Médias | C72: Stockage distant (S3, CDN, etc.) | D72: Grille | E72: =Matrice!O32 -> 6 | F72: MVP | H72: Filesystem Laravel (S3, Infomaniak Swiss Backup S3)
A73: Contenu | B73: Médias | C73: Gestion vidéo / audio / documents | D73: Grille | E73: =Matrice!O33 -> 10 | F73: MVP | H73: medialibrary
A74: Contenu | B74: Médias | C74: Upload par glisser-déposer / multiple | D74: Grille | E74: =Matrice!O34 -> 9 | F74: MVP | H74: Filament FileUpload (natif)
A75: Contenu | B75: Médias | C75: Détection des médias inutilisés | D75: Grille | E75: =Matrice!O35 -> 0 | F75: V1 | G75: Oui | H75: Index des références
A76: Contenu | B76: Médias | C76: Upload par morceaux (gros fichiers) | D76: Ajout (hors grille) | F76: MVP | H76: Livewire / Filament chunked upload | I76: Kirby
A77: Contenu | B77: Médias | C77: Import d'un média depuis une URL | D77: Ajout (hors grille) | F77: V2 | H77: Http + medialibrary addMediaFromUrl | I77: Payload
A78: Contenu | B78: Médias | C78: Upload direct du navigateur vers le stockage distant | D78: Ajout (hors grille) | F78: V2 | H78: URLs présignées S3 | I78: Payload
A79: Contenu | B79: Médias | C79: Renommage avec mise à jour des références | D79: Ajout (hors grille) | F79: V1 | G79: Oui | H79: UUID + références par ID | I79: Statamic
A80: Contenu | B80: Médias | C80: Filigrane (watermark) | D80: Ajout (hors grille) | F80: V2 | H80: Glide / Intervention Image | I80: Statamic, Grav
A81: Contenu | B81: Médias | C81: srcset / images responsives automatiques | D81: Ajout (hors grille) | F81: MVP | H81: spatie/laravel-medialibrary responsive images | I81: Grav, WordPress, Statamic
A82: Contenu | B82: Médias | C82: Intégrations oEmbed (YouTube, Vimeo…) | D82: Ajout (hors grille) | F82: V1 | H82: Package oEmbed | I82: WordPress, Kirby
A83: Contenu | B83: Médias | C83: Fichiers privés soumis aux permissions | D83: Ajout (hors grille) | F83: V1 | H83: Disque privé + URLs signées Laravel | I83: Drupal, Grav
A84: Contenu | B84: Médias | C84: Types de fichiers avec champs propres (templates de fichiers) | D84: Ajout (hors grille) | F84: V2 | H84: Collections medialibrary | I84: Kirby, Statamic
A85: Contenu | B85: Versioning et planification | C85: Brouillons | D85: Grille | E85: =Matrice!O36 -> 10 | F85: MVP | H85: Colonne statut + scopes
A86: Contenu | B86: Versioning et planification | C86: Historique des révisions | D86: Grille | E86: =Matrice!O37 -> 7 | F86: MVP | H86: Table de révisions (ex. mpociot/versionable)
A87: Contenu | B87: Versioning et planification | C87: Comparaison de versions (diff) | D87: Grille | E87: =Matrice!O38 -> 4 | F87: V1 | G87: Oui | H87: Diff JSON / texte
A88: Contenu | B88: Versioning et planification | C88: Restauration d'une révision | D88: Grille | E88: =Matrice!O39 -> 7 | F88: MVP | H88: Action Filament
A89: Contenu | B89: Versioning et planification | C89: Publication programmée | D89: Grille | E89: =Matrice!O40 -> 8 | F89: MVP | G89: Oui | H89: Évaluée à la lecture (published_at <= now), sans dépendre du planificateur
A90: Contenu | B90: Versioning et planification | C90: Dépublication programmée / expiration | D90: Grille | E90: =Matrice!O41 -> 4 | F90: V1 | H90: Évaluée à la lecture (unpublished_at)
A91: Contenu | B91: Versioning et planification | C91: Corbeille / suppression douce | D91: Grille | E91: =Matrice!O42 -> 6 | F91: MVP | H91: SoftDeletes + Filament TrashedFilter (natif)
A92: Contenu | B92: Versioning et planification | C92: Duplication de contenu | D92: Grille | E92: =Matrice!O43 -> 6 | F92: MVP | H92: Filament ReplicateAction (natif)
A93: Contenu | B93: Versioning et planification | C93: Liens d'aperçu partageables et expirables | D93: Ajout (hors grille) | F93: MVP | G93: Oui | H93: URLs signées temporaires Laravel | I93: Craft, Kirby, TallCMS, WordPress
A94: Contenu | B94: Versioning et planification | C94: Snapshots nommés et épinglés | D94: Ajout (hors grille) | F94: V2 | H94: Table de révisions | I94: TallCMS
A95: Contenu | B95: Versioning et planification | C95: Revue groupée de changements avant publication (workspaces) | D95: Ajout (hors grille) | F95: V2 | G95: Oui | H95: Logique applicative | I95: Drupal
A96: Contenu | B96: Versioning et planification | C96: Suivi créateur / dernier modificateur | D96: Ajout (hors grille) | F96: MVP | H96: Observers Eloquent | I96: October
A97: Contenu | B97: Versioning et planification | C97: Résumé des changements en attente de l'équipe | D97: Ajout (hors grille) | F97: V2 | H97: Logique applicative | I97: Kirby
A98: Contenu | B98: Recherche | C98: Recherche interne dans l'admin | D98: Grille | E98: =Matrice!O44 -> 10 | F98: MVP | H98: Filament global search (natif)
A99: Contenu | B99: Recherche | C99: Recherche front-end intégrée | D99: Grille | E99: =Matrice!O45 -> 8 | F99: V1 | H99: Laravel Scout driver database (compatible mutualisé)
A100: Contenu | B100: Recherche | C100: Recherche plein texte | D100: Grille | E100: =Matrice!O46 -> 3 | F100: V1 | H100: Scout + MySQL fulltext
A101: Contenu | B101: Recherche | C101: Index personnalisables (champs indexés) | D101: Grille | E101: =Matrice!O47 -> 4 | F101: V1 | H101: toSearchableArray() Scout
A102: Contenu | B102: Recherche | C102: Intégrations moteurs externes (Algolia, Meilisearch, Elasticsearch) | D102: Grille | E102: =Matrice!O48 -> 3 | F102: V1 | G102: Oui | H102: Drivers Scout, optionnels (hors mutualisé)
A103: Contenu | B103: Recherche | C103: Filtres / facettes | D103: Grille | E103: =Matrice!O49 -> 2 | F103: V2 | H103: Meilisearch facets
...

Sheet Matrice
A1: Bloc | B1: Catégorie | C1: Fonctionnalité | D1: WordPress | E1: Drupal | F1: Craft CMS | G1: Kirby | H1: Statamic | I1: October CMS | J1: Grav | K1: Payload | L1: TallCMS | M1: Lara Zeus Sky | N1: Nb natif | O1: Nb dispo (natif+officiel)
A2: Contenu | B2: Modélisation de contenu | C2: Types de contenu personnalisés (sans code) | D2: Officiel | E2: Natif | F2: Natif | G2: Absent | H2: Natif | I2: Partiel | J2: Partiel | K2: Absent | L2: Absent | M2: Absent | N2: =COUNTIF(D2:M2,"Natif") -> 3 | O2: =COUNTIF(D2:M2,"Natif")+COUNTIF(D2:M2,"Officiel") -> 4
A3: Contenu | B3: Modélisation de contenu | C3: Types de contenu définis en code (schéma versionnable) | D3: Natif | E3: Natif | F3: Natif | G3: Natif | H3: Natif | I3: Natif | J3: Natif | K3: Natif | L3: Partiel | M3: Partiel | N3: =COUNTIF(D3:M3,"Natif") -> 8 | O3: =COUNTIF(D3:M3,"Natif")+COUNTIF(D3:M3,"Officiel") -> 8
A4: Contenu | B4: Modélisation de contenu | C4: Champs personnalisés (bibliothèque de types de champs) | D4: Officiel | E4: Natif | F4: Natif | G4: Natif | H4: Natif | I4: Natif | J4: Natif | K4: Natif | L4: Partiel | M4: Absent | N4: =COUNTIF(D4:M4,"Natif") -> 7 | O4: =COUNTIF(D4:M4,"Natif")+COUNTIF(D4:M4,"Officiel") -> 8
A5: Contenu | B5: Modélisation de contenu | C5: Champs répétables / groupes de champs | D5: Officiel | E5: Tiers | F5: Natif | G5: Natif | H5: Natif | I5: Natif | J5: Natif | K5: Natif | L5: Partiel | M5: Absent | N5: =COUNTIF(D5:M5,"Natif") -> 6 | O5: =COUNTIF(D5:M5,"Natif")+COUNTIF(D5:M5,"Officiel") -> 7
A6: Contenu | B6: Modélisation de contenu | C6: Relations entre contenus (1-n, n-n) | D6: Officiel | E6: Natif | F6: Natif | G6: Natif | H6: Natif | I6: Natif | J6: Partiel | K6: Natif | L6: Partiel | M6: Partiel | N6: =COUNTIF(D6:M6,"Natif") -> 6 | O6: =COUNTIF(D6:M6,"Natif")+COUNTIF(D6:M6,"Officiel") -> 7
A7: Contenu | B7: Modélisation de contenu | C7: Relations bidirectionnelles / reverse lookup | D7: Officiel | E7: Partiel | F7: Partiel | G7: Partiel | H7: Tiers | I7: Natif | J7: Absent | K7: Natif | L7: Partiel | M7: Partiel | N7: =COUNTIF(D7:M7,"Natif") -> 2 | O7: =COUNTIF(D7:M7,"Natif")+COUNTIF(D7:M7,"Officiel") -> 3
A8: Contenu | B8: Modélisation de contenu | C8: Taxonomies (catégories, tags, vocabulaires personnalisés) | D8: Natif | E8: Natif | F8: Natif | G8: Partiel | H8: Natif | I8: Partiel | J8: Natif | K8: Partiel | L8: Partiel | M8: Natif | N8: =COUNTIF(D8:M8,"Natif") -> 6 | O8: =COUNTIF(D8:M8,"Natif")+COUNTIF(D8:M8,"Officiel") -> 6
A9: Contenu | B9: Modélisation de contenu | C9: Contenu hiérarchique (arborescence parent/enfant) | D9: Natif | E9: Partiel | F9: Natif | G9: Natif | H9: Natif | I9: Natif | J9: Natif | K9: Officiel | L9: Natif | M9: Natif | N9: =COUNTIF(D9:M9,"Natif") -> 8 | O9: =COUNTIF(D9:M9,"Natif")+COUNTIF(D9:M9,"Officiel") -> 9
A10: Contenu | B10: Modélisation de contenu | C10: Ensembles de champs réutilisables (fieldsets / blueprints) | D10: Officiel | E10: Partiel | F10: Natif | G10: Natif | H10: Natif | I10: Natif | J10: Natif | K10: Natif | L10: Absent | M10: Absent | N10: =COUNTIF(D10:M10,"Natif") -> 6 | O10: =COUNTIF(D10:M10,"Natif")+COUNTIF(D10:M10,"Officiel") -> 7
A11: Contenu | B11: Modélisation de contenu | C11: Contenus globaux / singletons (réglages de site) | D11: Officiel | E11: Partiel | F11: Natif | G11: Natif | H11: Natif | I11: Natif | J11: Natif | K11: Natif | L11: Natif | M11: Partiel | N11: =COUNTIF(D11:M11,"Natif") -> 7 | O11: =COUNTIF(D11:M11,"Natif")+COUNTIF(D11:M11,"Officiel") -> 8
A12: Contenu | B12: Modélisation de contenu | C12: Validation des champs (règles, champs obligatoires) | D12: Officiel | E12: Natif | F12: Natif | G12: Natif | H12: Natif | I12: Natif | J12: Natif | K12: Natif | L12: Natif | M12: Natif | N12: =COUNTIF(D12:M12,"Natif") -> 9 | O12: =COUNTIF(D12:M12,"Natif")+COUNTIF(D12:M12,"Officiel") -> 10
A13: Contenu | B13: Modélisation de contenu | C13: Champs conditionnels (affichage selon valeur) | D13: Officiel | E13: Tiers | F13: Natif | G13: Partiel | H13: Natif | I13: Natif | J13: Partiel | K13: Natif | L13: Natif | M13: Partiel | N13: =COUNTIF(D13:M13,"Natif") -> 5 | O13: =COUNTIF(D13:M13,"Natif")+COUNTIF(D13:M13,"Officiel") -> 6
... A212: Gouvernance | B212: Écosystème et communauté | C212: Taille de la communauté (forum, Discord) | D212: Info | E212: Info | F212: Info | G212: Info | H212: Info | I212: Info | J212: Info | K212: Info | L212: Info | M212: Info | N212: =COUNTIF(D212:M212,"Natif") -> 0 | O212: =COUNTIF(D212:M212,"Natif")+COUNTIF(D212:M212,"Officiel") -> 0

Sheet Détails
A1: Bloc | B1: Catégorie | C1: Fonctionnalité | D1: CMS | E1: Statut | F1: Détail | G1: Source
A2: Contenu | B2: Modélisation de contenu | C2: Types de contenu personnalisés (sans code) | D2: WordPress | E2: Officiel | F2: Secure Custom Fields (plugin WordPress.org, gratuit) permet d'enregistrer types de contenu et taxonomies via l'admin ; le cœur l'exige en code. | G2: https://wordpress.org/plugins/secure-custom-fields/
A3: Contenu | B3: Modélisation de contenu | C3: Types de contenu personnalisés (sans code) | D3: Drupal | E3: Natif | F3: Types de contenu (bundles de nœuds) créés et configurés depuis Structure > Types de contenu. | G3: https://www.drupal.org/docs/user_guide/en/structure-content-type.html
A4: Contenu | B4: Modélisation de contenu | C4: Types de contenu personnalisés (sans code) | D4: Craft CMS | E4: Natif | F4: Sections (Single, Channel, Structure) et types d'entrées globaux créés depuis Paramètres, sans code. | G4: https://craftcms.com/docs/5.x/reference/element-types/entries.html
A5: Contenu | B5: Modélisation de contenu | C5: Types de contenu personnalisés (sans code) | D5: Kirby | E5: Absent | F5: Les types (templates) se définissent par fichiers blueprints YAML/PHP ; aucun éditeur de schéma dans le Panel. | G5: https://getkirby.com/docs/guide/blueprints/introduction
A6: Contenu | B6: Modélisation de contenu | C6: Types de contenu personnalisés (sans code) | D6: Statamic | E6: Natif | F6: Collections, taxonomies, globals et blueprints créables depuis le Control Panel, illimités même en Core. | G6: https://statamic.dev/content-modeling/collections
A7: Contenu | B7: Modélisation de contenu | C7: Types de contenu personnalisés (sans code) | D7: October CMS | E7: Partiel | F7: Tailor crée types, tables et formulaires sans PHP, mais via blueprints YAML écrits dans l'éditeur backend ; pas de constructeur visuel. | G7: https://docs.octobercms.com/4.x/cms/tailor/introduction.html
A8: Contenu | B8: Modélisation de contenu | C8: Types de contenu personnalisés (sans code) | D8: Grav | E8: Partiel | F8: Types de pages et collections Flex définis par blueprints YAML ; aucun éditeur visuel de types dans Admin2. | G8: https://github.com/trilbymedia/grav-plugin-flex-objects
A9: Contenu | B9: Modélisation de contenu | C9: Types de contenu personnalisés (sans code) | D9: Payload | E9: Absent | F9: Les collections se déclarent uniquement en TypeScript dans payload.config ; aucun constructeur de schéma dans l'admin. | G9: https://payloadcms.com/docs/configuration/collections
A10: Contenu | B10: Modélisation de contenu | C10: Types de contenu personnalisés (sans code) | D10: TallCMS | E10: Absent | F10: Seulement deux types fixes (Pages et Articles) ; aucun constructeur de types de contenu dans l'admin. | G10: https://github.com/tallcms/tallcms/blob/main/docs/site-pages-posts.md
A11: Contenu | B11: Modélisation de contenu | C11: Types de contenu personnalisés (sans code) | D11: Lara Zeus Sky | E11: Absent | F11: Types figés : articles, pages, FAQ, bibliothèque ; aucun constructeur de types depuis l'admin. | G11: https://larazeus.com/docs/sky/v5/introduction
A12: Contenu | B12: Modélisation de contenu | C12: Types de contenu définis en code (schéma versionnable) | D12: WordPress | E12: Natif | F12: register_post_type() et register_taxonomy() en PHP dans un plugin ou thème, donc versionnables dans Git. | G12: https://developer.wordpress.org/plugins/post-types/registering-custom-post-types/
... A89: Contenu | B89: Modélisation de contenu | C89: Ensembles de champs réutilisables (fieldsets / blueprints) | D89: Payload | E89: Natif | F89: Les champs sont des objets TS réutilisables ; blockReferences permet de partager des blocs définis une seule fois. | G89: https://payloadcms.com/docs/fields/blocks
A90: Contenu | B90: Modélisation de contenu | C90: Ensembles de champs réutilisables (fieldsets / blueprints) | D90: TallCMS | E90: Absent | F90: Aucune notion de fieldset ou blueprint réutilisable ; les traits PHP des blocs sont le seul partage.
A91: Contenu | B91: Modélisation de contenu | C91: Ensembles de champs réutilisables (fieldsets / blueprints) | D91: Lara Zeus Sky | E91: Absent | F91: Aucun mécanisme de fieldsets ; uniquement la composition de schémas Filament en code.
A92: Contenu | B92: Modélisation de contenu | C92: Contenus globaux / singletons (réglages de site) | D92: WordPress | E92: Officiel | F92: Pages d'options de Secure Custom Fields ; le cœur propose seulement la Settings API en code. | G92: https://wordpress.org/plugins/secure-custom-fields/
A93: Contenu | B93: Modélisation de contenu | C93: Contenus globaux / singletons (réglages de site) | D93: Drupal | E93: Partiel | F93: Formulaires de configuration codés par module ; singletons éditables par contributeurs via Config Pages. | G93: https://www.drupal.org/project/config_pages
A94: Contenu | B94: Modélisation de contenu | C94: Contenus globaux / singletons (réglages de site) | D94: Craft CMS | E94: Natif | F94: Sections Single pour pages uniques et Global Sets pour réglages partagés accessibles partout dans Twig. | G94: https://craftcms.com/docs/5.x/reference/element-types/globals.html
A95: Contenu | B95: Modélisation de contenu | C95: Contenus globaux / singletons (réglages de site) | D95: Kirby | E95: Natif | F95: Objet $site avec son propre blueprint site.yml pour les réglages globaux ; pages uniques possibles. | G95: https://getkirby.com/docs/reference/panel/blueprints/site
A96: Contenu | B96: Modélisation de contenu | C96: Contenus globaux / singletons (réglages de site) | D96: Statamic | E96: Natif | F96: Global sets éditables dans le CP, accessibles partout dans les templates, localisables. | G96: https://statamic.dev/content-modeling/globals
A97: Contenu | B97: Modélisation de contenu | C97: Contenus globaux / singletons (réglages de site) | D97: October CMS | E97: Natif | F97: Blueprints global (réglages site, multisite possible) et single (entrée unique type page d'accueil). | G97: https://docs.octobercms.com/4.x/cms/tailor/blueprints.html
A98: Contenu | B98: Modélisation de contenu | C98: Contenus globaux / singletons (réglages de site) | D98: Grav | E98: Natif | F98: site.yaml et configuration de thème éditables comme réglages globaux, exposés à Twig. | G98: https://learn.getgrav.org/17/basics/grav-configuration
A99: Contenu | B99: Modélisation de contenu | C99: Contenus globaux / singletons (réglages de site) | D99: Payload | E99: Natif | F99: Globals : documents uniques (header, footer, réglages) avec versions et accès propres. | G99: https://payloadcms.com/docs/configuration/globals
A100: Contenu | B100: Modélisation de contenu | C100: Contenus globaux / singletons (réglages de site) | D100: TallCMS | E100: Natif | F100: Pages Site Settings et Global Defaults (identité, branding, contact, réseaux sociaux, maintenance) avec héritage. | G100: https://github.com/tallcms/tallcms/blob/main/docs/site-settings.md
A101: Contenu | B101: Modélisation de contenu | C101: Contenus globaux / singletons (réglages de site) | D101: Lara Zeus Sky | E101: Partiel | F101: Réglages limités au fichier config zeus.php (titre, description, couleur) ; pas d'écran de réglages. | G101: https://github.com/lara-zeus/sky/blob/main/config/zeus-sky.php
A102: Contenu | B102: Modélisation de contenu | C102: Validation des champs (règles, champs obligatoires) | D102: WordPress | E102: Officiel | F102: Champs obligatoires et validation dans Secure Custom Fields ; register_meta() permet un schéma JSON côté REST. | G102: https://wordpress.org/plugins/secure-custom-fields/
A103: Contenu | B103: Modélisation de contenu | C103: Validation des champs (règles, champs obligatoires) | D103: Drupal | E103: Natif | F103: Champs obligatoires, cardinalité, limites, et contraintes Symfony Validator sur entités et champs. | G103: https://www.drupal.org/docs/drupal-apis/entity-api/entity-validation-api
... A170: Contenu | B170: Édition et blocs | C170: Blocs imbriqués | D170: TallCMS | E170: Absent | F170: Les blocs sont des nœuds atomiques Tiptap configurés par modal ; pas d'imbrication de blocs dans des blocs. | G170: https://github.com/tallcms/tallcms/blob/main/docs/ref-rich-editor.md
A171: Contenu | B171: Édition et blocs | C171: Blocs imbriqués | D171: Lara Zeus Sky | E171: Absent | F171: Pas de système de blocs.
A172: Contenu | B172: Édition et blocs | C172: Blocs / patterns réutilisables (synchronisés) | D172: WordPress | E172: Natif | F172: Compositions synchronisées (ex-blocs réutilisables) avec Pattern Overrides pour contenus variables par instance. | G172: https://wordpress.org/documentation/article/reusable-blocks/
A173: Contenu | B173: Édition et blocs | C173: Blocs / patterns réutilisables (synchronisés) | D173: Drupal | E173: Natif | F173: Blocs de contenu réutilisables (bibliothèque de blocs) synchronisés ; les patterns Canvas sont en revanche des copies indépendantes. | G173: https://www.drupal.org/docs/user_guide/en/block-create-custom.html
A174: Contenu | B174: Édition et blocs | C174: Blocs / patterns réutilisables (synchronisés) | D174: Craft CMS | E174: Partiel | F174: Pas de patterns synchronisés natifs ; contournement courant via un champ Entries pointant vers des entrées « composants ». | G174: https://craftcms.com/docs/5.x/reference/field-types/entries.html
A175: Contenu | B175: Édition et blocs | C175: Blocs / patterns réutilisables (synchronisés) | D175: Kirby | E175: Tiers | F175: Pas de blocs synchronisés natifs ; plugins Block Reference (tearoom1) ou kirby-global-blocks (tobimori). | G175: https://packagist.org/packages/tobimori/kirby-global-blocks
A176: Contenu | B176: Édition et blocs | C176: Blocs / patterns réutilisables (synchronisés) | D176: Statamic | E176: Partiel | F176: Sets réutilisables via import de fieldsets (schéma), mais pas de blocs de contenu synchronisés ; contournement par entrées liées. | G176: https://statamic.dev/content-modeling/fieldsets
A177: Contenu | B177: Édition et blocs | C177: Blocs / patterns réutilisables (synchronisés) | D177: October CMS | E177: Partiel | F177: Snippets et content blocks réutilisables partout, mais pas de bibliothèque de blocs de contenu synchronisés gérée par l'éditeur. | G177: https://docs.octobercms.com/4.x/cms/themes/snippets.html
A178: Contenu | B178: Édition et blocs | C178: Blocs / patterns réutilisables (synchronisés) | D178: Grav | E178: Officiel | F178: Plugin Page Inject (gratuit) pour insérer le contenu d'une autre page, mis à jour partout. | G178: https://github.com/getgrav/grav-plugin-page-inject
A179: Contenu | B179: Édition et blocs | C179: Blocs / patterns réutilisables (synchronisés) | D179: Payload | E179: Partiel | F179: Pas de blocs synchronisés côté éditeur ; il faut une collection de blocs référencée par relationship. | G179: https://payloadcms.com/docs/fields/blocks
A180: Contenu | B180: Édition et blocs | C180: Blocs / patterns réutilisables (synchronisés) | D180: TallCMS | E180: Absent | F180: Duplication de bloc possible mais aucun bloc global synchronisé ni bibliothèque de patterns. | G180: https://github.com/tallcms/tallcms/blob/main/docs/ref-rich-editor.md
A181: Contenu | B181: Édition et blocs | C181: Blocs / patterns réutilisables (synchronisés) | D181: Lara Zeus Sky | E181: Absent | F181: Aucun bloc réutilisable synchronisé.
A182: Contenu | B182: Édition et blocs | C182: Support Markdown | D182: WordPress | E182: Partiel | F182: Le Markdown collé est converti en blocs et certains raccourcis Markdown sont reconnus ; pas de stockage Markdown (bloc Markdown via Jetpack). | G182: https://wordpress.org/documentation/article/keyboard-shortcuts-block-editor/
A183: Contenu | B183: Édition et blocs | C183: Support Markdown | D183: Drupal | E183: Tiers | F183: Module Markdown (filtre de texte) ; CKEditor 5 accepte seulement l'autoformatage de syntaxe Markdown à la saisie. | G183: https://www.drupal.org/project/markdown
A184: Contenu | B184: Édition et blocs | C184: Support Markdown | D184: Craft CMS | E184: Partiel | F184: Filtre Twig |markdown et élément de layout Markdown ; pas de champ éditeur Markdown natif (plugins tiers). | G184: https://craftcms.com/docs/5.x/reference/twig/filters.html
A185: Contenu | B185: Édition et blocs | C185: Support Markdown | D185: Kirby | E185: Natif | F185: Markdown/KirbyText dans textarea, bloc markdown, extension de contenu .md possible, parseur configurable. | G185: https://getkirby.com/docs/reference/system/options/markdown
A186: Contenu | B186: Édition et blocs | C186: Support Markdown | D186: Statamic | E186: Natif | F186: Fieldtype Markdown dédié, fichiers .md comme contenu et modifier markdown en template. | G186: https://statamic.dev/frontend/markdown
A187: Contenu | B187: Édition et blocs | C187: Support Markdown | D187: October CMS | E187: Natif | F187: Widget markdown editor, filtre Twig |md et content blocks .md. | G187: https://docs.octobercms.com/4.x/element/form/widget-markdown.html
A188: Contenu | B188: Édition et blocs | C188: Support Markdown | D188: Grav | E188: Natif | F188: Markdown est le format de stockage ; Parsedown Extra, GFM (tâches, autoliens), surlignage et API d'extension de syntaxe. | G188: https://github.com/getgrav/grav/blob/develop/CHANGELOG.md
A189: Contenu | B189: Édition et blocs | C189: Support Markdown | D189: Payload | E189: Natif | F189: Raccourcis Markdown dans Lexical et convertisseurs Lexical vers/depuis Markdown et MDX. | G189: https://payloadcms.com/docs/rich-text/converting-markdown
A190: Contenu | B190: Édition et blocs | C190: Support Markdown | D190: TallCMS | E190: Absent | F190: Aucune saisie ou import Markdown documenté pour le contenu (le Markdown ne sert qu'à la doc).
A191: Contenu | B191: Édition et blocs | C191: Support Markdown | D191: Lara Zeus Sky | E191: Natif | F191: MarkdownEditor de Filament sélectionnable comme éditeur de contenu. | G191: https://larazeus.com/docs/sky/v5/getting-started/editor
A192: Contenu | B192: Édition et blocs | C192: Édition en contexte (front-end) | D192: WordPress | E192: Partiel | F192: Le Site Editor offre une édition visuelle fidèle au rendu, mais pas d'édition directe sur le site public. | G192: https://wordpress.org/documentation/article/site-editor/
A193: Contenu | B193: Édition et blocs | C193: Édition en contexte (front-end) | D193: Drupal | E193: Officiel | F193: Drupal Canvas permet l'édition visuelle de la page ; Settings Tray et Quick Edit retirés du cœur. | G193: https://www.drupal.org/project/canvas
A194: Contenu | B194: Édition et blocs | C194: Édition en contexte (front-end) | D194: Craft CMS | E194: Absent | F194: Aucune édition sur le front ; seul un lien vers l'écran d'édition du panneau (cpEditUrl) est possible.
A195: Contenu | B195: Édition et blocs | C195: Édition en contexte (front-end) | D195: Kirby | E195: Tiers | F195: Pas d'édition front native ; plugins Admin Bar/Edit Button pour lier au Panel. Kirby 6 apporte un éditeur live côte à côte. | G195: https://getkirby.com/releases/6
A196: Contenu | B196: Édition et blocs | C196: Édition en contexte (front-end) | D196: Statamic | E196: Partiel | F196: Pas d'édition inline native ; seulement des barres de liens vers le CP via addons tiers (Simple Statamic Toolbar). | G196: https://statamic.com/addons/chrisvasey/simple-statamic-toolbar
A197: Contenu | B197: Édition et blocs | C197: Édition en contexte (front-end) | D197: October CMS | E197: Officiel | F197: Plugin RainLab.Editable (gratuit) pour content blocks, mais présenté comme preuve de concept et non testé sur v4. | G197: https://octobercms.com/plugin/rainlab-editable
A198: Contenu | B198: Édition et blocs | C198: Édition en contexte (front-end) | D198: Grav | E198: Absent | F198: Pas d'édition sur le site public ; l'édition passe par Admin2. | G198: https://github.com/getgrav/grav-plugin-admin2
A199: Contenu | B199: Édition et blocs | C199: Édition en contexte (front-end) | D199: Payload | E199: Officiel | F199: Payant : Visual Editor Enterprise annoncé (édition sur la page), encore « coming soon » ; admin-bar seulement en gratuit. | G199: https://payloadcms.com/enterprise
A200: Contenu | B200: Édition et blocs | C200: Édition en contexte (front-end) | D200: TallCMS | E200: Absent | F200: Édition uniquement dans le panneau Filament ; aucune édition sur le front.
A201: Contenu | B201: Édition et blocs | C201: Édition en contexte (front-end) | D201: Lara Zeus Sky | E201: Absent | F201: Édition uniquement dans le panneau Filament.
A202: Contenu | B202: Édition et blocs | C202: Live preview / aperçu avant publication | D202: WordPress | E202: Natif | F202: Aperçu des brouillons et modifications non publiées dans un nouvel onglet ; canvas iframé fidèle au thème. | G202: https://wordpress.org/documentation/article/preview-post/
A203: Contenu | B203: Édition et blocs | C203: Live preview / aperçu avant publication | D203: Drupal | E203: Natif | F203: Bouton Aperçu des nœuds ; Canvas offre un aperçu en direct pendant l'édition. | G203: https://www.drupal.org/docs/user_guide/en/content-create.html
A204: Contenu | B204: Édition et blocs | C204: Live preview / aperçu avant publication | D204: Craft CMS | E204: Natif | F204: Live Preview en vue partagée rafraîchie à chaque autosave, liens d'aperçu tokenisés partageables ; cibles multiples en Team/Pro. | G204: https://craftcms.com/docs/5.x/system/drafts-revisions.html
A205: Contenu | B205: Édition et blocs | C205: Live preview / aperçu avant publication | D205: Kirby | E205: Natif | F205: Kirby 5 : vue Preview des changements non publiés, mode comparaison, synchro du défilement (5.3). | G205: https://getkirby.com/releases/5/changes
A206: Contenu | B206: Édition et blocs | C206: Live preview / aperçu avant publication | D206: Statamic | E206: Natif | F206: Live Preview avec hot-reload, preview targets multiples, fenêtre détachable, disponible en Core. | G206: https://statamic.dev/control-panel/live-preview
A207: Contenu | B207: Édition et blocs | C207: Live preview / aperçu avant publication | D207: October CMS | E207: Natif | F207: Bouton Preview Tailor ouvrant la page CMS associée avec jeton de prévisualisation temporaire, brouillons compris. | G207: https://github.com/octobercms/october/blob/develop/modules/tailor/behaviors/PreviewController.php
A208: Contenu | B208: Édition et blocs | C208: Live preview / aperçu avant publication | D208: Grav | E208: Officiel | F208: Aperçu Markdown côte à côte et volet de prévisualisation par langue dans plugin Admin2 (gratuit, livré dans le paquet grav-admin). | G208: https://github.com/getgrav/grav-plugin-admin2/blob/develop/CHANGELOG.md
A209: Contenu | B209: Édition et blocs | C209: Live preview / aperçu avant publication | D209: Payload | E209: Natif | F209: Live Preview en iframe synchronisée en temps réel, plus Draft Preview via URL de prévisualisation. | G209: https://payloadcms.com/docs/live-preview/overview
A210: Contenu | B210: Édition et blocs | C210: Live preview / aperçu avant publication | D210: TallCMS | E210: Natif | F210: Bouton Preview dans le thème réel, plus liens d'aperçu partageables à jetons expirables et révocables. | G210: https://github.com/tallcms/tallcms/blob/main/docs/ref-publishing.md
A211: Contenu | B211: Édition et blocs | C211: Live preview / aperçu avant publication | D211: Lara Zeus Sky | E211: Partiel | F211: Action « Ouvrir » vers la page publique ; pas d'aperçu de brouillon dédié. | G211: https://github.com/lara-zeus/sky/blob/main/src/Filament/Resources/PostResource.php
A212: Contenu | B212: Édition et blocs | C212: Aperçu responsive (mobile/tablette) | D212: WordPress | E212: Natif | F212: Aperçu bureau/tablette/mobile dans l'éditeur ; 7.1 ajoute des styles par point de rupture configurable. | G212: https://wordpress.org/news/2026/08/mary-lou/
A213: Contenu | B213: Édition et blocs | C213: Aperçu responsive (mobile/tablette) | D213: Drupal | E213: Officiel | F213: Canvas propose des aperçus mobile, tablette, bureau et grand écran ; rien d'équivalent dans le formulaire classique. | G213: https://imagexmedia.com/blog/drupal-canvas-tour-content-authoring
... A216: Contenu | B216: Édition et blocs | C216: Aperçu responsive (mobile/tablette) | D216: Statamic | E216: Natif | F216: Sélecteur d'appareils dans Live Preview, tailles configurables dans config/statamic/live_preview.php. | G216: https://statamic.dev/control-panel/live-preview
A217: Contenu | B217: Édition et blocs | C217: Aperçu responsive (mobile/tablette) | D217: October CMS | E217: Absent | F217: L'aperçu ouvre la page front dans un onglet ; aucun sélecteur d'appareil intégré.
A218: Contenu | B218: Édition et blocs | C218: Aperçu responsive (mobile/tablette) | D218: Grav | E218: ? | F218: Aucun aperçu par taille d'écran documenté dans Admin2.
A219: Contenu | B219: Édition et blocs | C219: Aperçu responsive (mobile/tablette) | D219: Payload | E219: Natif | F219: Option breakpoints du Live Preview : tailles d'appareil sélectionnables dans la barre d'outils. | G219: https://payloadcms.com/docs/live-preview/overview#breakpoints
A220: Contenu | B220: Édition et blocs | C220: Aperçu responsive (mobile/tablette) | D220: TallCMS | E220: Absent | F220: L'aperçu s'ouvre dans un nouvel onglet sans sélecteur de taille d'écran. | G220: https://github.com/tallcms/tallcms/blob/main/docs/ref-publishing.md
A221: Contenu | B221: Édition et blocs | C221: Aperçu responsive (mobile/tablette) | D221: Lara Zeus Sky | E221: Absent | F221: Aucun aperçu par appareil.
A222: Contenu | B222: Édition et blocs | C222: Raccourcis clavier / slash commands | D222: WordPress | E222: Natif | F222: Commande / pour insérer un bloc, raccourcis clavier et palette de commandes Ctrl/Cmd+K dans tout l'admin. | G222: https://wordpress.org/documentation/article/keyboard-shortcuts-block-editor/
A223: Contenu | B223: Édition et blocs | C223: Raccourcis clavier / slash commands | D223: Drupal | E223: Partiel | F223: Raccourcis et autoformatage CKEditor 5 ; pas de slash commands natives ; navigation clavier admin via Coffee. | G223: https://www.drupal.org/project/coffee
A224: Contenu | B224: Édition et blocs | C224: Raccourcis clavier / slash commands | D224: Craft CMS | E224: Partiel | F224: Raccourcis Cmd+S, Cmd+Shift+S, sélection Shift-clic ; pas de slash commands natives. | G224: https://craftcms.com/docs/5.x/system/control-panel.html
A225: Contenu | B225: Édition et blocs | C225: Raccourcis clavier / slash commands | D225: Kirby | E225: Partiel | F225: Raccourcis clavier dans blocs et writer (ajout 4.0), pas de slash commands natives. | G225: https://getkirby.com/releases/4
A226: Contenu | B226: Édition et blocs | C226: Raccourcis clavier / slash commands | D226: Statamic | E226: Partiel | F226: Raccourcis clavier (⌘K, ⌘S…) et API Statamic.$keys ; pas de slash commands documentées dans Bard. | G226: https://statamic.dev/control-panel/keyboard-shortcuts
A227: Contenu | B227: Édition et blocs | C227: Raccourcis clavier / slash commands | D227: October CMS | E227: Partiel | F227: Raccourcis clavier dans l'éditeur CMS et la barre d'outils document (save, hotkeys) ; pas de slash commands. | G227: https://octobercms.com/support/article/rn-42
A228: Contenu | B228: Édition et blocs | C228: Raccourcis clavier / slash commands | D228: Grav | E228: Partiel | F228: Admin2 gère des raccourcis clavier et la navigation au clavier ; slash commands non confirmées hors Editor Pro. | G228: https://github.com/getgrav/grav-plugin-admin2/blob/develop/CHANGELOG.md
A229: Contenu | B229: Édition et blocs | C229: Raccourcis clavier / slash commands | D229: Payload | E229: Natif | F229: Menu slash et raccourcis clavier (gras, italique…) dans Lexical ; Ctrl+S pour enregistrer. | G229: https://payloadcms.com/docs/rich-text/official-features
A230: Contenu | B230: Édition et blocs | C230: Raccourcis clavier / slash commands | D230: TallCMS | E230: Natif | F230: Commande / façon Notion pour insérer un bloc, navigation clavier, undo ⌘Z sur réordonnancement. | G230: https://github.com/tallcms/tallcms/blob/main/docs/ref-rich-editor.md
A231: Contenu | B231: Édition et blocs | C231: Raccourcis clavier / slash commands | D231: Lara Zeus Sky | E231: Natif | F231: Raccourcis de l'éditeur TipTap de Filament (gras, listes…) ; pas de slash commands spécifiques à Sky. | G231: https://filamentphp.com/docs/5.x/forms/rich-editor
A232: Contenu | B232: Édition et blocs | C232: Sauvegarde automatique des brouillons | D232: WordPress | E232: Natif | F232: Autosave périodique (révision autosave) et sauvegarde locale du navigateur en cas de perte de connexion. | G232: https://wordpress.org/documentation/article/revisions/
A233: Contenu | B233: Édition et blocs | C233: Sauvegarde automatique des brouillons | D233: Drupal | E233: Officiel | F233: Canvas sauvegarde automatiquement ; formulaires classiques via Autosave Form (tiers, inclus dans Drupal CMS). | G233: https://www.drupal.org/project/canvas
... A307: Contenu | B307: Médias | C307: Stockage distant (S3, CDN, etc.) | D307: October CMS | E307: Natif | F307: Disques Laravel Flysystem (S3, etc.) configurables pour médias, uploads et assets de thème. | G307: https://docs.octobercms.com/4.x/cms/media/providers.html
A308: Contenu | B308: Médias | C308: Stockage distant (S3, CDN, etc.) | D308: Grav | E308: Absent | F308: Médias stockés sur le système de fichiers local ; aucun adaptateur S3 officiel identifié.
A309: Contenu | B309: Médias | C309: Stockage distant (S3, CDN, etc.) | D309: Payload | E309: Officiel | F309: Adaptateurs @payloadcms/storage-s3, -azure, -gcs, -r2, -vercel-blob, -uploadthing. | G309: https://payloadcms.com/docs/upload/storage-adapters
A310: Contenu | B310: Médias | C310: Stockage distant (S3, CDN, etc.) | D310: TallCMS | E310: Natif | F310: Disques Laravel : S3, R2, Spaces, B2, MinIO auto-détectés ; disque dédié via TALLCMS_MEDIA_DISK. | G310: https://github.com/tallcms/tallcms/blob/main/docs/site-media.md
A311: Contenu | B311: Médias | C311: Stockage distant (S3, CDN, etc.) | D311: Lara Zeus Sky | E311: Natif | F311: Disque et répertoire d'upload configurables (uploadDisk/uploadDirectory), donc tout disque Laravel dont S3. | G311: https://larazeus.com/docs/sky/v5/getting-started/configuration
A312: Contenu | B312: Médias | C312: Gestion vidéo / audio / documents | D312: WordPress | E312: Natif | F312: Upload et blocs Vidéo, Audio, Fichier, Playlist (7.1) avec lecteur intégré ; hébergement vidéo avancé via VideoPress (officiel, payant). | G312: https://wordpress.org/news/2026/08/mary-lou/
A313: Contenu | B313: Médias | C313: Gestion vidéo / audio / documents | D313: Drupal | E313: Natif | F313: Types de média Document, Audio, Vidéo locale et Vidéo distante (oEmbed YouTube/Vimeo) dans le cœur. | G313: https://www.drupal.org/docs/core-modules-and-themes/core-modules/media-module
A314: Contenu | B314: Médias | C314: Gestion vidéo / audio / documents | D314: Craft CMS | E314: Natif | F314: Tous types de fichiers gérés avec filtrage par kind ; aperçu audio/vidéo dans l'écran d'édition (5.5). | G314: https://craftcms.com/docs/5.x/reference/element-types/assets.html
A315: Contenu | B315: Médias | C315: Gestion vidéo / audio / documents | D315: Kirby | E315: Natif | F315: Types de fichiers image, vidéo, audio, documents, code ; aperçus Panel vidéo/audio/PDF depuis 5.0. | G315: https://getkirby.com/releases/5
A316: Contenu | B316: Médias | C316: Gestion vidéo / audio / documents | D316: Statamic | E316: Natif | F316: Tout type de fichier stockable, miniatures vidéo via FFmpeg, fieldtype Video (YouTube, Vimeo, Cloudflare Stream). | G316: https://statamic.dev/frontend/assets
A317: Contenu | B317: Médias | C317: Gestion vidéo / audio / documents | D317: October CMS | E317: Natif | F317: Media Manager gère tout type de fichier avec partials lecteurs audio/vidéo personnalisables. | G317: https://docs.octobercms.com/4.x/cms/media/introduction.html
...

Sheet Hors grille
A1: CMS | B1: Catégorie | C1: Fonctionnalité | D1: Statut | E1: Détail | F1: Source
A2: WordPress | B2: Extensibilité | C2: Abilities API (registre unifié des capacités, PHP et JS) | D2: Natif | E2: Registre de capacités typées (JSON Schema) exposables aux agents, à la palette de commandes et à MCP. | F2: https://make.wordpress.org/core/2026/05/14/wordpress-7-0-field-guide/
A3: WordPress | B3: IA | C3: WP AI Client et écran Connecteurs | D3: Natif | E3: Interface d'IA agnostique du fournisseur dans le cœur, clés Anthropic/OpenAI/Google gérées dans Réglages > Connecteurs. | F3: https://make.wordpress.org/core/2026/05/14/wordpress-7-0-field-guide/
A4: WordPress | B4: Édition et blocs | C4: Block Bindings API | D4: Natif | E4: Lier des attributs de blocs à des métadonnées ou sources personnalisées sans bloc dédié. | F4: https://developer.wordpress.org/block-editor/reference-guides/block-api/block-bindings/
A5: WordPress | B5: Édition et blocs | C5: Pattern Overrides | D5: Natif | E5: Compositions synchronisées dont certains contenus restent modifiables par instance, y compris pour blocs personnalisés (7.0). | F5: https://make.wordpress.org/core/2026/05/14/wordpress-7-0-field-guide/
A6: WordPress | B6: Édition et blocs | C6: Visibilité des blocs par appareil | D6: Natif | E6: Masquer un bloc en front ou par viewport (mobile/tablette/bureau) depuis 6.9/7.0. | F6: https://make.wordpress.org/core/2026/05/14/wordpress-7-0-field-guide/
A7: WordPress | B7: Thèmes et front-end | C7: Styles globaux / theme.json (design tokens) | D7: Natif | E7: Palette, typographie, espacements et styles par bloc centralisés et éditables visuellement. | F7: https://developer.wordpress.org/themes/global-settings-and-styles/
A8: WordPress | B8: Thèmes et front-end | C8: Styles responsive et états interactifs | D8: Natif | E8: Styles par point de rupture configurable et états hover/focus/active sans CSS (7.1). | F8: https://wordpress.org/news/2026/08/mary-lou/
A9: WordPress | B9: Thèmes et front-end | C9: Bibliothèque de polices (Font Library) | D9: Natif | E9: Installation et gestion de polices Google ou uploadées, utilisable avec tous types de thèmes. | F9: https://make.wordpress.org/core/2026/05/14/wordpress-7-0-field-guide/
A10: WordPress | B10: Thèmes et front-end | C10: Interactivity API | D10: Natif | E10: API déclarative de directives (data-wp-*) pour l'interactivité front rendue côté serveur. | F10: https://developer.wordpress.org/block-editor/reference-guides/interactivity-api/
A11: WordPress | B11: Édition et blocs | C11: Query Loop et blocs dynamiques | D11: Natif | E11: Bloc Boucle de requête configurable visuellement pour lister des contenus filtrés. | F11: https://wordpress.org/documentation/article/query-loop-block/
A12: WordPress | B12: Contenu | C12: Commentaires avec modération | D12: Natif | E12: Système de commentaires intégré avec modération, liste noire, Akismet en option. | F12: https://wordpress.org/documentation/article/comments-screen/
... A298: Lara Zeus Sky | B298: Utilisateurs | C298: Modèle auteur configurable | D298: Natif | E298: Relation author basée sur le modèle utilisateur de auth, surchargeable (ex. LDAP). | F298: https://larazeus.com/docs/sky/v5/advanced/models

Sheet Inspirations
A1: CMS | B1: Type | C1: Élément
A2: WordPress | B2: Point fort | C2: Écosystème inégalé : plus de 76 000 plugins et 8 700 thèmes gratuits, installables en un clic depuis l'admin.
A3: WordPress | B3: Point fort | C3: Éditeur de blocs et Site Editor matures : patterns synchronisés avec overrides, styles globaux theme.json, styles responsive et états interactifs sans CSS.
A4: WordPress | B4: Point fort | C4: Système de hooks actions/filtres omniprésent, permettant de modifier presque tout comportement sans toucher au cœur.
A5: WordPress | B5: Point fort | C5: Mises à jour en un clic et automatiques (cœur, plugins, traductions) avec rollback et mode de récupération après erreur fatale.
A6: WordPress | B6: Point fort | C6: Socle IA en avance : WP AI Client, écran Connecteurs, Abilities API et plugin MCP Adapter pour exposer le site aux agents.
A7: WordPress | B7: Point fort | C7: Outils RGPD natifs (export/effacement, page de confidentialité guidée) et notes de relecture intégrées à l'éditeur.
A8: WordPress | B8: Point fort | C8: Hébergeable partout, y compris sur mutualisé bas de gamme, avec installeur web et WP-CLI très complet.
A9: WordPress | B9: Point fort | C9: Rétrocompatibilité forte et communauté mondiale (traductions dans plus de 200 locales).
A10: WordPress | B10: À reprendre | C10: Un registre d'« abilities » typées (JSON Schema) partagé entre palette de commandes, API et serveur MCP, à brancher sur les actions Filament.
A11: WordPress | B11: À reprendre | C11: Patterns synchronisés avec overrides par instance : blocs réutilisables dont certains champs restent éditables localement.
A12: WordPress | B12: À reprendre | C12: Design tokens centralisés type theme.json, éditables visuellement et consommés par le front et l'éditeur.
... A218: Lara Zeus Sky | B218: Limite | C218: Interface non traduite en français pour les libellés Sky (anglais, arabe, turc).
